{"_type":"export","__export_format":4,"__export_date":"2023-06-26T17:01:52.685Z","__export_source":"insomnia.desktop.app:v2023.2.2","resources":[{"_id":"req_81a1bb61e6a640f3a5871899359a3624","parentId":"fld_db739268ae7a46bc99591dc82a25b314","modified":1687784804180,"created":1686922682383,"url":"{{ _.download_signed_url }}","name":"Download File by SignedURL","description":"","method":"GET","body":{},"parameters":[],"headers":[{"id":"pair_6f4babe762e342f5a902399b0d5e0b4a","name":"data-partition-id","value":"{{ _['data-partition-id'] }}","description":""},{"id":"pair_50d70e2b72ed468a8df443efd748472e","name":"Content-Type","value":"text/csv","description":""}],"authentication":{},"metaSortKey":-1686074148911,"isPrivate":false,"settingStoreCookies":true,"settingSendCookies":true,"settingDisableRenderRequestBody":false,"settingEncodeUrl":true,"settingRebuildPath":true,"settingFollowRedirects":"global","_type":"request"},{"_id":"fld_db739268ae7a46bc99591dc82a25b314","parentId":"wrk_c6691554431948b888837f433dd73cbc","modified":1686922682340,"created":1686922682340,"name":"OSDU Quick start","description":"","environment":{},"environmentPropertyOrder":null,"metaSortKey":-1686074148874,"_type":"request_group"},{"_id":"wrk_c6691554431948b888837f433dd73cbc","parentId":null,"modified":1687798614741,"created":1687798614741,"name":"TestandoImportacao","description":"","scope":"design","_type":"workspace"},{"_id":"req_ec64734718ad4109a7a9da4461d0efb2","parentId":"fld_db739268ae7a46bc99591dc82a25b314","modified":1686922682381,"created":1686922682381,"url":"{{FILE_HOST}}/files/{{ _.record_id }}/downloadURL","name":"File API - Get Download Url","description":"","method":"GET","body":{},"parameters":[],"headers":[{"name":"Data-Partition-Id","value":"{{ _['data-partition-id'] }}","id":"pair_01c644626705433990dd81da45cdcde9"}],"authentication":{"type":"oauth2","grantType":"client_credentials","accessTokenUrl":"{{ _.client_credentials }}","clientId":"{{ _.CLIENT_ID }}","clientSecret":"{{ _.CLIENT_SECRET }}"},"metaSortKey":-1686074148910,"isPrivate":false,"settingStoreCookies":true,"settingSendCookies":true,"settingDisableRenderRequestBody":false,"settingEncodeUrl":true,"settingRebuildPath":true,"settingFollowRedirects":"global","_type":"request"},{"_id":"req_00a1ee3240e447249fe25e6096418bfb","parentId":"fld_db739268ae7a46bc99591dc82a25b314","modified":1686922682379,"created":1686922682379,"url":"{{ _.SEARCH_HOST }}/query","name":"Search API - text search","description":"","method":"POST","body":{"mimeType":"application/json","text":"{\n \"kind\": \"osdu:wks:dataset--File.Generic:1.0.0\",\n \"limit\": 300,\n \"query\": \"\\\"Dataset Volve - production data\\\"\"\n}"},"parameters":[],"headers":[{"name":"data-partition-id","value":"{{ _['data-partition-id'] }}","id":"pair_da9068de5b6d46cca056f159a22a1512"},{"name":"Content-Type","value":"application/json","id":"pair_80049f19142e45eab0f982fb80242dc1"}],"authentication":{"type":"oauth2","grantType":"client_credentials","accessTokenUrl":"{{ _.client_credentials }}","clientId":"{{ _.CLIENT_ID }}","clientSecret":"{{ _.CLIENT_SECRET }}"},"metaSortKey":-1686074148908,"isPrivate":false,"settingStoreCookies":true,"settingSendCookies":true,"settingDisableRenderRequestBody":false,"settingEncodeUrl":true,"settingRebuildPath":true,"settingFollowRedirects":"global","_type":"request"},{"_id":"req_f130c6b5c7454b848dd2d2958d831a44","parentId":"fld_db739268ae7a46bc99591dc82a25b314","modified":1686922682376,"created":1686922682376,"url":"{{SEARCH_HOST}}/query","name":"Search API - search by id","description":"","method":"POST","body":{"mimeType":"application/json","text":"{\n \"kind\": \"*:*:*:*\",\n \"limit\": 300,\n \"query\": \"id: \\\"{{record_id}}\\\"\"\n}"},"parameters":[],"headers":[{"name":"data-partition-id","value":"{{ _['data-partition-id'] }}","id":"pair_ecd819534f594b94a43b44b22a841ef9"},{"name":"Content-Type","value":"application/json","id":"pair_6d5463d5efc54620a5569b3d5343444f"}],"authentication":{"type":"oauth2","grantType":"client_credentials","accessTokenUrl":"{{ _.client_credentials }}","clientId":"{{ _.CLIENT_ID }}","clientSecret":"{{ _.CLIENT_SECRET }}"},"metaSortKey":-1686074148907,"isPrivate":false,"settingStoreCookies":true,"settingSendCookies":true,"settingDisableRenderRequestBody":false,"settingEncodeUrl":true,"settingRebuildPath":true,"settingFollowRedirects":"global","_type":"request"},{"_id":"req_777cdb453d694e7ca7d278916f10c955","parentId":"fld_db739268ae7a46bc99591dc82a25b314","modified":1687783947883,"created":1686922682374,"url":"{{STORAGE_HOST}}/records/{{ _.record_id }}","name":"Storage API - search by id","description":"","method":"GET","body":{},"parameters":[],"headers":[{"name":"Content-Type","value":"application/json","id":"pair_aacdebd2e98a4853a5582b485c7db449"},{"name":"data-partition-id","value":"{{ _['data-partition-id'] }}","id":"pair_0d3819842b9e45e4a379a186a37a5250"}],"authentication":{"type":"oauth2","grantType":"client_credentials","accessTokenUrl":"{{ _.client_credentials }}","clientId":"{{ _.CLIENT_ID }}","clientSecret":"{{ _.CLIENT_SECRET }}"},"metaSortKey":-1686074148905,"isPrivate":false,"settingStoreCookies":true,"settingSendCookies":true,"settingDisableRenderRequestBody":false,"settingEncodeUrl":true,"settingRebuildPath":true,"settingFollowRedirects":"global","_type":"request"},{"_id":"req_3d8ff7a0106e43aeb61fa535e5abeed3","parentId":"fld_db739268ae7a46bc99591dc82a25b314","modified":1687783742555,"created":1686922682363,"url":"{{ _.FILE_HOST }}/files/metadata","name":"File API - Create File Metadata","description":"","method":"POST","body":{"mimeType":"application/json","text":"{\n    \"data\": {\n        \"Endian\": \"BIG\",\n        \"Description\": \"Data Loading of production data\",\n        \"DatasetProperties\": {\n            \"FileSourceInfo\": {\n\n                \"FileSource\": \"{{ _.file_source }}\",\n                \"Name\": \"Wellhead_Temperature_Well888\",\n                \"PreLoadFilePath\": \"\",\n                \"PreloadFileCreateUser\": \"Data Management Team\",\n                \"PreloadFileModifyDate\": \"June 26 2023\",\n                \"PreloadFileModifyUser\": \"Data Management Team\"\n            }\n        },\n        \"TotalSize\": \"2288KB\",\n        \"Source\": \"Scada System\",\n        \"Name\": \"Production data of Volve\"\n    },\n    \"kind\": \"osdu:wks:dataset--File.Generic:1.0.0\",\n    \"acl\": {\n        \"viewers\": [\n            \"{{ _.New_ViewerDataGroup }}@{{ _.domain }}\"\n        ],\n        \"owners\": [\n            \"{{ _.New_OwnerDataGroup }}@{{ _.domain }}\"\n        ]\n    },\n    \"legal\": {\n        \"legaltags\": [\n            \"{{ _.tagName }}\"\n        ],\n        \"otherRelevantDataCountries\": [\n            \"BR\"\n        ],\n        \"status\": \"compliant\"\n    }\n}"},"parameters":[],"headers":[{"name":"Data-Partition-Id","value":"{{ _['data-partition-id'] }}","id":"pair_24e7bf82f5584edabb29b3cbb74519d0"},{"name":"Content-Type","value":"application/json","id":"pair_cae0350d1cdd4a518a2f6ff3615531dd"}],"authentication":{"type":"oauth2","grantType":"client_credentials","accessTokenUrl":"{{ _.client_credentials }}","clientId":"{{ _.CLIENT_ID }}","clientSecret":"{{ _.CLIENT_SECRET }}"},"metaSortKey":-1686074148900,"isPrivate":false,"settingStoreCookies":true,"settingSendCookies":true,"settingDisableRenderRequestBody":false,"settingEncodeUrl":true,"settingRebuildPath":true,"settingFollowRedirects":"global","_type":"request"},{"_id":"req_94eea7cdd5b742898df9e30bbae60f90","parentId":"fld_db739268ae7a46bc99591dc82a25b314","modified":1687459444465,"created":1686922682361,"url":"{{ _.upload_signedURL }}","name":"File API - Data Ingestion - UploadFile by SignedURL","description":"","method":"PUT","body":{"mimeType":"application/octet-stream","fileName":"C:\\Users\\jay_e\\Desktop\\Wellhead_Temperature_Well888.csv"},"parameters":[],"headers":[{"name":"Content-Type","value":"text/csv"}],"authentication":{},"metaSortKey":-1686074148899,"isPrivate":false,"settingStoreCookies":true,"settingSendCookies":true,"settingDisableRenderRequestBody":false,"settingEncodeUrl":true,"settingRebuildPath":true,"settingFollowRedirects":"global","_type":"request"},{"_id":"req_2de9b7a160b740c1a922bd214c03fb3a","parentId":"fld_db739268ae7a46bc99591dc82a25b314","modified":1686922682359,"created":1686922682359,"url":"{{ _.FILE_HOST }}/files/uploadURL","name":"File API - Data Ingestion - Get Upload Url","description":"","method":"GET","body":{"mimeType":"application/json","text":""},"parameters":[],"headers":[{"name":"Data-Partition-Id","value":"{{ _['data-partition-id'] }}","id":"pair_01f9ddd57aa44372b8d9ce788ec5491f"},{"name":"Content-Type","value":"application/json"}],"authentication":{"type":"oauth2","grantType":"client_credentials","accessTokenUrl":"{{ _.client_credentials }}","clientId":"{{ _.CLIENT_ID }}","clientSecret":"{{ _.CLIENT_SECRET }}"},"metaSortKey":-1686074148897,"isPrivate":false,"settingStoreCookies":true,"settingSendCookies":true,"settingDisableRenderRequestBody":false,"settingEncodeUrl":true,"settingRebuildPath":true,"settingFollowRedirects":"global","_type":"request"},{"_id":"req_30d5573ff6e64b5f86e919bd0690f6fc","parentId":"fld_db739268ae7a46bc99591dc82a25b314","modified":1687453167709,"created":1686922682356,"url":"{{ _.STORAGE_HOST }}/records","name":"Storage API - Create Organisation record with kind","description":"","method":"PUT","body":{"mimeType":"application/json","text":"[\n\t{\n\t\t\"id\": \"osdu:master-data--Organisation:Operator01\",\n\t\t\"kind\": \"osdu:wks:master-data--Organisation:1.1.0\",\n\t\t\"acl\": {\n\t\t\t\"owners\": [\n\t\t\t\t\"{{ _.New_OwnerDataGroup }}@{{ _.domain }}\"\n\t\t\t],\n\t\t\t\"viewers\": [\n\t\t\t\t\"{{ _.New_ViewerDataGroup }}@{{ _.domain }}\"\n\t\t\t]\n\t\t},\n\t\t\"legal\": {\n\t\t\t\"legaltags\": [\n\t\t\t\t\"{{ _.tagName }}\"\n\t\t\t],\n\t\t\t\"otherRelevantDataCountries\": [\n\t\t\t\t\"BR\"\n\t\t\t],\n\t\t\t\"status\": \"compliant\"\n\t\t},\n\t\t\"data\": {\n\t\t\t\"ResourceHomeRegionID\": \"osdu:reference-data--OSDURegion:AWSEastUSA:\",\n\t\t\t\"ResourceHostRegionIDs\": [\n\t\t\t\t\"osdu:reference-data--OSDURegion:AWSEastUSA:\"\n\t\t\t],\n\t\t\t\"ResourceCurationStatus\": \"osdu:reference-data--ResourceCurationStatus:CREATED:\",\n\t\t\t\"ResourceLifecycleStatus\": \"osdu:reference-data--ResourceLifecycleStatus:LOADING:\",\n\t\t\t\"ResourceSecurityClassification\": \"osdu:reference-data--ResourceSecurityClassification:RESTRICTED:\",\n\t\t\t\"ExistenceKind\": \"osdu:reference-data--ExistenceKind:Active:\",\n\t\t\t\"TechnicalAssuranceTypeID\": \"osdu:reference-data--TechnicalAssuranceType:Certified:\",\n\t\t\t\"OrganisationName\": \"Operator 01\",\n\t\t\t\"InternalOrganisationIndicator\": true,\n\t\t\t\"OrganisationPurposeDescription\": \"Engeering services for production of oil and gas.\",\n\t\t\t\"OrganisationDescription\": \"Service providers are companies that do not have oil and gas platforms. Operator01 provides engineering services for platforms.\",\n\t\t\t\"OrganisationTypeID\": \"osdu:reference-data--OrganisationType:EngeeringServices:\",\n\t\t\t\"ExtensionProperties\": {}\n\t\t}\n\t}\n]"},"parameters":[{"name":"skipdupes","value":"true","disabled":true}],"headers":[{"name":"data-partition-id","value":"{{ _['data-partition-id'] }}","id":"pair_1b8e4fd8991f4b56ad693c3ffcc400fb"},{"name":"Accept","value":"application/json","id":"pair_12b5af01be3c49bca502c0f5049c1235"},{"name":"Content-Type","value":"application/json","id":"pair_e7cebbfb86d34ed9b85f9d85a0d48d94"}],"authentication":{"type":"oauth2","grantType":"client_credentials","accessTokenUrl":"{{ _.client_credentials }}","clientId":"{{ _.CLIENT_ID }}","clientSecret":"{{ _.CLIENT_SECRET }}"},"metaSortKey":-1686074148896,"isPrivate":false,"settingStoreCookies":true,"settingSendCookies":true,"settingDisableRenderRequestBody":false,"settingEncodeUrl":true,"settingRebuildPath":true,"settingFollowRedirects":"global","_type":"request"},{"_id":"req_4214ec56909e45ec80b238d9ac57945b","parentId":"fld_db739268ae7a46bc99591dc82a25b314","modified":1687462384326,"created":1687458777364,"url":"{{ _.STORAGE_HOST }}/records","name":"Storage API - Create WPC record with kind","description":"","method":"PUT","body":{"mimeType":"application/json","text":"[\n\t{\n\t\t\"id\": \"osdu:work-product-component--TimeSeries:WellheadPressureWell888\",\n\t\t\"kind\": \"osdu:wks:work-product-component--TimeSeries:1.1.0\",\n\t\t\"acl\": {\n\t\t\t\"owners\": [\n\t\t\t\t\"{{ _.New_OwnerDataGroup }}@{{ _.domain }}\"\n\t\t\t],\n\t\t\t\"viewers\": [\n\t\t\t\t\"{{ _.New_ViewerDataGroup }}@{{ _.domain }}\"\n\t\t\t]\n\t\t},\n\t\t\"legal\": {\n\t\t\t\"legaltags\": [\n\t\t\t\t\"{{ _.tagName }}\"\n\t\t\t],\n\t\t\t\"otherRelevantDataCountries\": [\n\t\t\t\t\"BR\"\n\t\t\t],\n\t\t\t\"status\": \"compliant\"\n\t\t},\n\t\t\"meta\": [],\n\t\t\"data\": {\n\t\t\t\"Source\": \"XX System\",\n\t\t\t\"Datasets\": [\n\t\t\t\t\"osdu:dataset--File.Generic:b7abdf6c-60d7-4c60-ad37-b70c6a1cbd5f:\"\n\t\t\t],\n\t\t\t\"IsExtendedLoad\": true,\n\t\t\t\"IsDiscoverable\": true,\n\t\t\t\"TechnicalAssurances\": [\n\t\t\t\t{\n\t\t\t\t\t\"TechnicalAssuranceTypeID\": \"osdu:reference-data--TechnicalAssuranceType:Trusted:\",\n\t\t\t\t\t\"Reviewers\": [\n\t\t\t\t\t\t{\n\t\t\t\t\t\t\t\"RoleTypeID\": \"osdu:reference-data--ContactRoleType:ProjectManager:\",\n\t\t\t\t\t\t\t\"OrganisationID\": \"osdu:master-data--Organisation:Operator01:\",\n\t\t\t\t\t\t\t\"Name\": \"Employ 001\"\n\t\t\t\t\t\t}\n\t\t\t\t\t],\n\t\t\t\t\t\"EffectiveDate\": \"2023-06-22\"\n\t\t\t\t}\n\t\t\t],\n\t\t\t\"Name\": \"Wellhead_Temperature_Well888.csv\",\n\t\t\t\"Description\": \"A CSV file that contains wellhead temeperature data of the well 888. An extended well test generated these data.\",\n\t\t\t\"WellboreID\": \"osdu:master-data--Wellbore:Wellbore1234:\",\n\t\t\t\"WellID\": \"osdu:master-data--Well:Well888:\",\n\t\t\t\"ExtensionProperties\": {\n\t\t\t\t\"Sensor\": \"Temperature sensor\",\n\t\t\t\t\"SensorID\": \"ABC-ABC\",\n\t\t\t\t\"Type\": \"Welhead temperature\",\n\t\t\t\t\"UnitOfMeasure\": \"kgf/cm²\",\n\t\t\t\t\"OriginFile\": \"1254236_zz\"\n\t\t\t},\n\t\t\t\"SchemaFormatTypeID\": \"osdu:reference-data--SchemaFormatType:TabSeparatedColumnarText:\"\n\t\t}\n\t}\n]"},"parameters":[{"name":"skipdupes","value":"true","disabled":true}],"headers":[{"name":"data-partition-id","value":"{{ _['data-partition-id'] }}","id":"pair_1b8e4fd8991f4b56ad693c3ffcc400fb"},{"name":"Accept","value":"application/json","id":"pair_12b5af01be3c49bca502c0f5049c1235"},{"name":"Content-Type","value":"application/json","id":"pair_e7cebbfb86d34ed9b85f9d85a0d48d94"}],"authentication":{"type":"oauth2","grantType":"client_credentials","accessTokenUrl":"{{ _.client_credentials }}","clientId":"{{ _.CLIENT_ID }}","clientSecret":"{{ _.CLIENT_SECRET }}"},"metaSortKey":-1686074148895.875,"isPrivate":false,"settingStoreCookies":true,"settingSendCookies":true,"settingDisableRenderRequestBody":false,"settingEncodeUrl":true,"settingRebuildPath":true,"settingFollowRedirects":"global","_type":"request"},{"_id":"req_60740ae1c3f24339b3d282b7921f364d","parentId":"fld_db739268ae7a46bc99591dc82a25b314","modified":1687455169114,"created":1687455019024,"url":"{{ _.STORAGE_HOST }}/records","name":"Storage API - Create Well record with kind","description":"","method":"PUT","body":{"mimeType":"application/json","text":"[\n\t{\n\t\t\"id\": \"osdu:master-data--Well:Well888\",\n\t\t\"kind\": \"osdu:wks:master-data--Well:1.2.0\",\n\t\t\"acl\": {\n\t\t\t\"owners\": [\n\t\t\t\t\"{{ _.New_OwnerDataGroup }}@{{ _.domain }}\"\n\t\t\t],\n\t\t\t\"viewers\": [\n\t\t\t\t\"{{ _.New_ViewerDataGroup }}@{{ _.domain }}\"\n\t\t\t]\n\t\t},\n\t\t\"legal\": {\n\t\t\t\"legaltags\": [\n\t\t\t\t\"{{ _.tagName }}\"\n\t\t\t],\n\t\t\t\"otherRelevantDataCountries\": [\n\t\t\t\t\"BR\"\n\t\t\t],\n\t\t\t\"status\": \"compliant\"\n\t\t},\n\t\t\"meta\": [],\n\t\t\"data\": {\n\t\t\t\"Source\": \"Company name or system\",\n\t\t\t\"ExistenceKind\": \"osdu:reference-data--ExistenceKind:Active:\",\n\t\t\t\"GeoContexts\": [\n\t\t\t\t{\n\t\t\t\t\t\"BasinID\": \"osdu:master-data--Basin:BasinName:\",\n\t\t\t\t\t\"GeoTypeID\": \"osdu:reference-data--BasinType:ArcWrenchOceanContinent:\"\n\t\t\t\t}\n\t\t\t],\n\t\t\t\"SpatialLocation\": {\n\t\t\t\t\"SpatialLocationCoordinatesDate\": \"2020-02-13T09:13:15.55Z\",\n\t\t\t\t\"QuantitativeAccuracyBandID\": \"osdu:reference-data--QuantitativeAccuracyBand:Length.LessThan1m:\",\n\t\t\t\t\"QualitativeSpatialAccuracyTypeID\": \"osdu:reference-data--QualitativeSpatialAccuracyType:Assumed:\",\n\t\t\t\t\"CoordinateQualityCheckPerformedBy\": \"Example CoordinateQualityCheckPerformedBy\",\n\t\t\t\t\"CoordinateQualityCheckDateTime\": \"2020-02-13T09:13:15.55Z\",\n\t\t\t\t\"CoordinateQualityCheckRemarks\": [\n\t\t\t\t\t\"Example CoordinateQualityCheckRemarks\"\n\t\t\t\t],\n\t\t\t\t\"AsIngestedCoordinates\": {\n\t\t\t\t\t\"type\": \"AnyCrsFeatureCollection\",\n\t\t\t\t\t\"CoordinateReferenceSystemID\": \"osdu:reference-data--CoordinateReferenceSystem:BoundProjected:EPSG::32021_EPSG::15851:\",\n\t\t\t\t\t\"VerticalCoordinateReferenceSystemID\": \"osdu:reference-data--CoordinateReferenceSystem:Vertical:EPSG::5714:\",\n\t\t\t\t\t\"VerticalUnitID\": \"osdu:reference-data--UnitOfMeasure:m:\",\n\t\t\t\t\t\"persistableReferenceCrs\": \"{\\\"authCode\\\":{\\\"auth\\\":\\\"OSDU\\\",\\\"code\\\":\\\"32021079\\\"},\\\"lateBoundCRS\\\":{\\\"authCode\\\":{\\\"auth\\\":\\\"EPSG\\\",\\\"code\\\":\\\"32021\\\"},\\\"name\\\":\\\"NAD_1927_StatePlane_North_Dakota_South_FIPS_3302\\\",\\\"type\\\":\\\"LBC\\\",\\\"ver\\\":\\\"PE_10_9_1\\\",\\\"wkt\\\":\\\"PROJCS[\\\\\\\"NAD_1927_StatePlane_North_Dakota_South_FIPS_3302\\\\\\\",GEOGCS[\\\\\\\"GCS_North_American_1927\\\\\\\",DATUM[\\\\\\\"D_North_American_1927\\\\\\\",SPHEROID[\\\\\\\"Clarke_1866\\\\\\\",6378206.4,294.9786982]],PRIMEM[\\\\\\\"Greenwich\\\\\\\",0.0],UNIT[\\\\\\\"Degree\\\\\\\",0.0174532925199433]],PROJECTION[\\\\\\\"Lambert_Conformal_Conic\\\\\\\"],PARAMETER[\\\\\\\"False_Easting\\\\\\\",2000000.0],PARAMETER[\\\\\\\"False_Northing\\\\\\\",0.0],PARAMETER[\\\\\\\"Central_Meridian\\\\\\\",-100.5],PARAMETER[\\\\\\\"Standard_Parallel_1\\\\\\\",46.18333333333333],PARAMETER[\\\\\\\"Standard_Parallel_2\\\\\\\",47.48333333333333],PARAMETER[\\\\\\\"Latitude_Of_Origin\\\\\\\",45.66666666666666],UNIT[\\\\\\\"Foot_US\\\\\\\",0.3048006096012192],AUTHORITY[\\\\\\\"EPSG\\\\\\\",32021]]\\\"},\\\"name\\\":\\\"NAD27 * OGP-Usa Conus / North Dakota CS27 South zone [32021,15851]\\\",\\\"singleCT\\\":{\\\"authCode\\\":{\\\"auth\\\":\\\"EPSG\\\",\\\"code\\\":\\\"15851\\\"},\\\"name\\\":\\\"NAD_1927_To_WGS_1984_79_CONUS\\\",\\\"type\\\":\\\"ST\\\",\\\"ver\\\":\\\"PE_10_9_1\\\",\\\"wkt\\\":\\\"GEOGTRAN[\\\\\\\"NAD_1927_To_WGS_1984_79_CONUS\\\\\\\",GEOGCS[\\\\\\\"GCS_North_American_1927\\\\\\\",DATUM[\\\\\\\"D_North_American_1927\\\\\\\",SPHEROID[\\\\\\\"Clarke_1866\\\\\\\",6378206.4,294.9786982]],PRIMEM[\\\\\\\"Greenwich\\\\\\\",0.0],UNIT[\\\\\\\"Degree\\\\\\\",0.0174532925199433]],GEOGCS[\\\\\\\"GCS_WGS_1984\\\\\\\",DATUM[\\\\\\\"D_WGS_1984\\\\\\\",SPHEROID[\\\\\\\"WGS_1984\\\\\\\",6378137.0,298.257223563]],PRIMEM[\\\\\\\"Greenwich\\\\\\\",0.0],UNIT[\\\\\\\"Degree\\\\\\\",0.0174532925199433]],METHOD[\\\\\\\"NADCON\\\\\\\"],PARAMETER[\\\\\\\"Dataset_conus\\\\\\\",0.0],OPERATIONACCURACY[5.0],AUTHORITY[\\\\\\\"EPSG\\\\\\\",15851]]\\\"},\\\"type\\\":\\\"EBC\\\",\\\"ver\\\":\\\"PE_10_9_1\\\"}\",\n\t\t\t\t\t\"persistableReferenceVerticalCrs\": \"{\\\"authCode\\\":{\\\"auth\\\":\\\"EPSG\\\",\\\"code\\\":\\\"5714\\\"},\\\"name\\\":\\\"MSL_Height\\\",\\\"type\\\":\\\"LBC\\\",\\\"ver\\\":\\\"PE_10_9_1\\\",\\\"wkt\\\":\\\"VERTCS[\\\\\\\"MSL_Height\\\\\\\",VDATUM[\\\\\\\"Mean_Sea_Level\\\\\\\"],PARAMETER[\\\\\\\"Vertical_Shift\\\\\\\",0.0],PARAMETER[\\\\\\\"Direction\\\\\\\",1.0],UNIT[\\\\\\\"Meter\\\\\\\",1.0],AUTHORITY[\\\\\\\"EPSG\\\\\\\",5714]]\\\"}\",\n\t\t\t\t\t\"persistableReferenceUnitZ\": \"{\\\"scaleOffset\\\":{\\\"scale\\\":1.0,\\\"offset\\\":0.0},\\\"symbol\\\":\\\"m\\\",\\\"baseMeasurement\\\":{\\\"ancestry\\\":\\\"Length\\\",\\\"type\\\":\\\"UM\\\"},\\\"type\\\":\\\"USO\\\"}\",\n\t\t\t\t\t\"features\": [\n\t\t\t\t\t\t{\n\t\t\t\t\t\t\t\"type\": \"AnyCrsFeature\",\n\t\t\t\t\t\t\t\"properties\": {},\n\t\t\t\t\t\t\t\"geometry\": {\n\t\t\t\t\t\t\t\t\"type\": \"AnyCrsPoint\",\n\t\t\t\t\t\t\t\t\"coordinates\": [\n\t\t\t\t\t\t\t\t\t12345.6,\n\t\t\t\t\t\t\t\t\t12345.6\n\t\t\t\t\t\t\t\t],\n\t\t\t\t\t\t\t\t\"bbox\": [\n\t\t\t\t\t\t\t\t\t12345.6,\n\t\t\t\t\t\t\t\t\t12345.6,\n\t\t\t\t\t\t\t\t\t12345.6,\n\t\t\t\t\t\t\t\t\t12345.6\n\t\t\t\t\t\t\t\t]\n\t\t\t\t\t\t\t},\n\t\t\t\t\t\t\t\"bbox\": [\n\t\t\t\t\t\t\t\t12345.6,\n\t\t\t\t\t\t\t\t12345.6,\n\t\t\t\t\t\t\t\t12345.6,\n\t\t\t\t\t\t\t\t12345.6\n\t\t\t\t\t\t\t]\n\t\t\t\t\t\t}\n\t\t\t\t\t],\n\t\t\t\t\t\"bbox\": [\n\t\t\t\t\t\t12345.6,\n\t\t\t\t\t\t12345.6,\n\t\t\t\t\t\t12345.6,\n\t\t\t\t\t\t12345.6\n\t\t\t\t\t]\n\t\t\t\t},\n\t\t\t\t\"Wgs84Coordinates\": {\n\t\t\t\t\t\"type\": \"FeatureCollection\",\n\t\t\t\t\t\"features\": [\n\t\t\t\t\t\t{\n\t\t\t\t\t\t\t\"type\": \"Feature\",\n\t\t\t\t\t\t\t\"properties\": {},\n\t\t\t\t\t\t\t\"geometry\": {\n\t\t\t\t\t\t\t\t\"type\": \"Point\",\n\t\t\t\t\t\t\t\t\"coordinates\": [\n\t\t\t\t\t\t\t\t\t12345.6,\n\t\t\t\t\t\t\t\t\t12345.6\n\t\t\t\t\t\t\t\t],\n\t\t\t\t\t\t\t\t\"bbox\": [\n\t\t\t\t\t\t\t\t\t12345.6,\n\t\t\t\t\t\t\t\t\t12345.6,\n\t\t\t\t\t\t\t\t\t12345.6,\n\t\t\t\t\t\t\t\t\t12345.6\n\t\t\t\t\t\t\t\t]\n\t\t\t\t\t\t\t},\n\t\t\t\t\t\t\t\"bbox\": [\n\t\t\t\t\t\t\t\t12345.6,\n\t\t\t\t\t\t\t\t12345.6,\n\t\t\t\t\t\t\t\t12345.6,\n\t\t\t\t\t\t\t\t12345.6\n\t\t\t\t\t\t\t]\n\t\t\t\t\t\t}\n\t\t\t\t\t],\n\t\t\t\t\t\"bbox\": [\n\t\t\t\t\t\t12345.6,\n\t\t\t\t\t\t12345.6,\n\t\t\t\t\t\t12345.6,\n\t\t\t\t\t\t12345.6\n\t\t\t\t\t]\n\t\t\t\t},\n\t\t\t\t\"SpatialParameterTypeID\": \"osdu:reference-data--SpatialParameterType:Outline:\",\n\t\t\t\t\"SpatialGeometryTypeID\": \"osdu:reference-data--SpatialGeometryType:Point:\"\n\t\t\t},\n\t\t\t\"TechnicalAssuranceTypeID\": \"osdu:reference-data--TechnicalAssuranceType:Certified:\",\n\t\t\t\"FacilityTypeID\": \"osdu:reference-data--FacilityType:Well:\",\n\t\t\t\"FacilityOperators\": [\n\t\t\t\t{\n\t\t\t\t\t\"FacilityOperatorID\": \"123-XXX\",\n\t\t\t\t\t\"FacilityOperatorOrganisationID\": \"osdu:master-data--Organisation:Operator01:\",\n\t\t\t\t\t\"EffectiveDateTime\": \"2020-02-13T09:13:15.55Z\",\n\t\t\t\t\t\"TerminationDateTime\": \"\"\n\t\t\t\t}\n\t\t\t],\n\t\t\t\"InitialOperatorID\": \"osdu:master-data--Organisation:Operator01:\",\n\t\t\t\"CurrentOperatorID\": \"osdu:master-data--Organisation:Operator01:\",\t\t\t\n\t\t\t\"OperatingEnvironmentID\": \"osdu:reference-data--OperatingEnvironment:Offshore:\",\n\t\t\t\"FacilityStates\": [\n\t\t\t\t{\n\t\t\t\t\t\"EffectiveDateTime\": \"2020-02-13T09:13:15.55Z\",\n\t\t\t\t\t\"TerminationDateTime\": \"2020-02-13T09:13:15.55Z\",\n\t\t\t\t\t\"FacilityStateTypeID\": \"osdu:reference-data--FacilityStateType:Operating:\"\n\t\t\t\t}\n\t\t\t],\n\t\t\t\"FacilityEvents\": [\n\t\t\t\t{\n\t\t\t\t\t\"FacilityEventTypeID\": \"osdu:reference-data--FacilityEventType:Drilling%20Start:\",\n\t\t\t\t\t\"EffectiveDateTime\": \"2012-12-03T02:30:00+08:00\"\n\t\t\t\t},\n\t\t\t\t{\n\t\t\t\t\t\"FacilityEventTypeID\": \"osdu:reference-data--FacilityEventType:Drilling%20Finish:\",\n\t\t\t\t\t\"EffectiveDateTime\": \"2012-12-25T19:30:00+08:00\"\n\t\t\t\t}\n\t\t\t],\n\t\t\t\"FacilitySpecifications\": [],\n\t\t\t\"InterestTypeID\": \"osdu:reference-data--WellInterestType:Yes:\",\n\t\t\t\"BusinessIntentionID\": \"osdu:reference-data--WellBusinessIntention:Appraise:\",\n\t\t\t\"RoleID\": \"osdu:reference-data--WellRole:Produce:\",\n\t\t\t\"HistoricalInterests\": [\n\t\t\t\t{\n\t\t\t\t\t\"InterestTypeID\": \"osdu:reference-data--WellInterestType:Yes:\",\n\t\t\t\t\t\"EffectiveDateTime\": \"2020-02-13\",\n\t\t\t\t\t\"TerminationDateTime\": \"\"\n\t\t\t\t}\n\t\t\t],\n\t\t\t\"WasBusinessInterestFinancialOperated\": true,\n\t\t\t\"WasBusinessInterestFinancialNonOperated\": true,\n\t\t\t\"WasBusinessInterestObligatory\": true,\n\t\t\t\"WasBusinessInterestTechnical\": true,\n\t\t\t\"ConditionID\": \"osdu:reference-data--WellCondition:Active:\",\n\t\t\t\"OutcomeID\": \"osdu:reference-data--WellBusinessIntentionOutcome:Achieved:\",\n\t\t\t\"ExtensionProperties\": {}\n\t\t}\n\t}\n]"},"parameters":[{"name":"skipdupes","value":"true","disabled":true}],"headers":[{"name":"data-partition-id","value":"{{ _['data-partition-id'] }}","id":"pair_1b8e4fd8991f4b56ad693c3ffcc400fb"},{"name":"Accept","value":"application/json","id":"pair_12b5af01be3c49bca502c0f5049c1235"},{"name":"Content-Type","value":"application/json","id":"pair_e7cebbfb86d34ed9b85f9d85a0d48d94"}],"authentication":{"type":"oauth2","grantType":"client_credentials","accessTokenUrl":"{{ _.client_credentials }}","clientId":"{{ _.CLIENT_ID }}","clientSecret":"{{ _.CLIENT_SECRET }}"},"metaSortKey":-1686074148895.75,"isPrivate":false,"settingStoreCookies":true,"settingSendCookies":true,"settingDisableRenderRequestBody":false,"settingEncodeUrl":true,"settingRebuildPath":true,"settingFollowRedirects":"global","_type":"request"},{"_id":"req_7f9f465beaa549c8a005fe6c81acd67b","parentId":"fld_db739268ae7a46bc99591dc82a25b314","modified":1687455673505,"created":1687455523231,"url":"{{ _.STORAGE_HOST }}/records","name":"Storage API - Create Wellbore record with kind","description":"","method":"PUT","body":{"mimeType":"application/json","text":"[\n  {\n    \"id\": \"osdu:master-data--Wellbore:Welbore1234\",\n    \"kind\": \"osdu:wks:master-data--Wellbore:1.2.0\",    \n    \"acl\": {\n      \"owners\": [\n        \"{{ _.New_OwnerDataGroup }}@{{ _.domain }}\"\n      ],\n      \"viewers\": [\n        \"{{ _.New_ViewerDataGroup }}@{{ _.domain }}\"\n      ]\n    },\n    \"legal\": {\n      \"legaltags\": [\n        \"{{ _.tagName }}\"\n      ],\n      \"otherRelevantDataCountries\": [\n        \"BR\"\n      ],\n      \"status\": \"compliant\"\n    },    \n    \"meta\": [\n      {\n        \"kind\": \"Unit\",\n        \"name\": \"m\",\n        \"persistableReference\": \"{\\\"abcd\\\":{\\\"a\\\":0.0,\\\"b\\\":1.0,\\\"c\\\":1.0,\\\"d\\\":0.0},\\\"symbol\\\":\\\"m\\\",\\\"baseMeasurement\\\":{\\\"ancestry\\\":\\\"L\\\",\\\"type\\\":\\\"UM\\\"},\\\"type\\\":\\\"UAD\\\"}\",\n        \"unitOfMeasureID\": \"osdu:reference-data--UnitOfMeasure:m:\",\n        \"propertyNames\": [\n          \"FacilitySpecifications[0].FacilitySpecificationQuantity\",\n          \"VerticalMeasurements[0].VerticalMeasurement\"\n        ]\n      }\n    ],\n    \"data\": {\n      \"Source\": \"Company or system\",\n      \"ExistenceKind\": \"osdu:reference-data--ExistenceKind:Active:\",\n      \"GeoContexts\": [\n        {\n          \"BasinID\": \"osdu:master-data--Basin:BasinName:\",\n          \"FieldID\": \"osdu:master-data--Field:FieldName:\"\n        }\n      ],\n      \"SpatialLocation\": {\n        \"SpatialLocationCoordinatesDate\": \"2020-02-13T09:13:15.55Z\",\n        \"QuantitativeAccuracyBandID\": \"osdu:reference-data--QuantitativeAccuracyBand:Length.LessThan1m:\",\n        \"QualitativeSpatialAccuracyTypeID\": \"osdu:reference-data--QualitativeSpatialAccuracyType:Assumed:\",\n        \"CoordinateQualityCheckPerformedBy\": \"Example CoordinateQualityCheckPerformedBy\",\n        \"CoordinateQualityCheckDateTime\": \"2020-02-13T09:13:15.55Z\",\n        \"CoordinateQualityCheckRemarks\": [\n          \"Example CoordinateQualityCheckRemarks\"\n        ],\n        \"AsIngestedCoordinates\": {\n          \"type\": \"AnyCrsFeatureCollection\",\n          \"CoordinateReferenceSystemID\": \"osdu:reference-data--CoordinateReferenceSystem:BoundProjected:EPSG::32021_EPSG::15851:\",\n          \"VerticalCoordinateReferenceSystemID\": \"osdu:reference-data--CoordinateReferenceSystem:Vertical:EPSG::5714:\",\n          \"VerticalUnitID\": \"osdu:reference-data--UnitOfMeasure:m:\",\n          \"persistableReferenceCrs\": \"{\\\"authCode\\\":{\\\"auth\\\":\\\"OSDU\\\",\\\"code\\\":\\\"32021079\\\"},\\\"lateBoundCRS\\\":{\\\"authCode\\\":{\\\"auth\\\":\\\"EPSG\\\",\\\"code\\\":\\\"32021\\\"},\\\"name\\\":\\\"NAD_1927_StatePlane_North_Dakota_South_FIPS_3302\\\",\\\"type\\\":\\\"LBC\\\",\\\"ver\\\":\\\"PE_10_9_1\\\",\\\"wkt\\\":\\\"PROJCS[\\\\\\\"NAD_1927_StatePlane_North_Dakota_South_FIPS_3302\\\\\\\",GEOGCS[\\\\\\\"GCS_North_American_1927\\\\\\\",DATUM[\\\\\\\"D_North_American_1927\\\\\\\",SPHEROID[\\\\\\\"Clarke_1866\\\\\\\",6378206.4,294.9786982]],PRIMEM[\\\\\\\"Greenwich\\\\\\\",0.0],UNIT[\\\\\\\"Degree\\\\\\\",0.0174532925199433]],PROJECTION[\\\\\\\"Lambert_Conformal_Conic\\\\\\\"],PARAMETER[\\\\\\\"False_Easting\\\\\\\",2000000.0],PARAMETER[\\\\\\\"False_Northing\\\\\\\",0.0],PARAMETER[\\\\\\\"Central_Meridian\\\\\\\",-100.5],PARAMETER[\\\\\\\"Standard_Parallel_1\\\\\\\",46.18333333333333],PARAMETER[\\\\\\\"Standard_Parallel_2\\\\\\\",47.48333333333333],PARAMETER[\\\\\\\"Latitude_Of_Origin\\\\\\\",45.66666666666666],UNIT[\\\\\\\"Foot_US\\\\\\\",0.3048006096012192],AUTHORITY[\\\\\\\"EPSG\\\\\\\",32021]]\\\"},\\\"name\\\":\\\"NAD27 * OGP-Usa Conus / North Dakota CS27 South zone [32021,15851]\\\",\\\"singleCT\\\":{\\\"authCode\\\":{\\\"auth\\\":\\\"EPSG\\\",\\\"code\\\":\\\"15851\\\"},\\\"name\\\":\\\"NAD_1927_To_WGS_1984_79_CONUS\\\",\\\"type\\\":\\\"ST\\\",\\\"ver\\\":\\\"PE_10_9_1\\\",\\\"wkt\\\":\\\"GEOGTRAN[\\\\\\\"NAD_1927_To_WGS_1984_79_CONUS\\\\\\\",GEOGCS[\\\\\\\"GCS_North_American_1927\\\\\\\",DATUM[\\\\\\\"D_North_American_1927\\\\\\\",SPHEROID[\\\\\\\"Clarke_1866\\\\\\\",6378206.4,294.9786982]],PRIMEM[\\\\\\\"Greenwich\\\\\\\",0.0],UNIT[\\\\\\\"Degree\\\\\\\",0.0174532925199433]],GEOGCS[\\\\\\\"GCS_WGS_1984\\\\\\\",DATUM[\\\\\\\"D_WGS_1984\\\\\\\",SPHEROID[\\\\\\\"WGS_1984\\\\\\\",6378137.0,298.257223563]],PRIMEM[\\\\\\\"Greenwich\\\\\\\",0.0],UNIT[\\\\\\\"Degree\\\\\\\",0.0174532925199433]],METHOD[\\\\\\\"NADCON\\\\\\\"],PARAMETER[\\\\\\\"Dataset_conus\\\\\\\",0.0],OPERATIONACCURACY[5.0],AUTHORITY[\\\\\\\"EPSG\\\\\\\",15851]]\\\"},\\\"type\\\":\\\"EBC\\\",\\\"ver\\\":\\\"PE_10_9_1\\\"}\",\n          \"persistableReferenceVerticalCrs\": \"{\\\"authCode\\\":{\\\"auth\\\":\\\"EPSG\\\",\\\"code\\\":\\\"5714\\\"},\\\"name\\\":\\\"MSL_Height\\\",\\\"type\\\":\\\"LBC\\\",\\\"ver\\\":\\\"PE_10_9_1\\\",\\\"wkt\\\":\\\"VERTCS[\\\\\\\"MSL_Height\\\\\\\",VDATUM[\\\\\\\"Mean_Sea_Level\\\\\\\"],PARAMETER[\\\\\\\"Vertical_Shift\\\\\\\",0.0],PARAMETER[\\\\\\\"Direction\\\\\\\",1.0],UNIT[\\\\\\\"Meter\\\\\\\",1.0],AUTHORITY[\\\\\\\"EPSG\\\\\\\",5714]]\\\"}\",\n          \"persistableReferenceUnitZ\": \"{\\\"scaleOffset\\\":{\\\"scale\\\":1.0,\\\"offset\\\":0.0},\\\"symbol\\\":\\\"m\\\",\\\"baseMeasurement\\\":{\\\"ancestry\\\":\\\"Length\\\",\\\"type\\\":\\\"UM\\\"},\\\"type\\\":\\\"USO\\\"}\",\n          \"features\": [\n            {\n              \"type\": \"AnyCrsFeature\",\n              \"properties\": {},\n              \"geometry\": {\n                \"type\": \"AnyCrsPoint\",\n                \"coordinates\": [\n                  12345.6,\n                  12345.6\n                ],\n                \"bbox\": [\n                  12345.6,\n                  12345.6,\n                  12345.6,\n                  12345.6\n                ]\n              },\n              \"bbox\": [\n                12345.6,\n                12345.6,\n                12345.6,\n                12345.6\n              ]\n            }\n          ],\n          \"bbox\": [\n            12345.6,\n            12345.6,\n            12345.6,\n            12345.6\n          ]\n        },\n        \"Wgs84Coordinates\": {\n          \"type\": \"FeatureCollection\",\n          \"features\": [\n            {\n              \"type\": \"Feature\",\n              \"properties\": {},\n              \"geometry\": {\n                \"type\": \"Point\",\n                \"coordinates\": [\n                  12345.6,\n                  12345.6\n                ],\n                \"bbox\": [\n                  12345.6,\n                  12345.6,\n                  12345.6,\n                  12345.6\n                ]\n              },\n              \"bbox\": [\n                12345.6,\n                12345.6,\n                12345.6,\n                12345.6\n              ]\n            }\n          ],\n          \"bbox\": [\n            12345.6,\n            12345.6,\n            12345.6,\n            12345.6\n          ]\n        },\n\n        \"SpatialParameterTypeID\": \"osdu:reference-data--SpatialParameterType:Outline:\",\n        \"SpatialGeometryTypeID\": \"osdu:reference-data--SpatialGeometryType:Point:\"\n      },\n      \"TechnicalAssuranceTypeID\": \"osdu:reference-data--TechnicalAssuranceType:Certified:\",      \n      \"FacilityTypeID\": \"osdu:reference-data--FacilityType:Wellbore:\",\n      \"FacilityName\": \"Wellbore 1234\",\n      \"FacilityOperators\": [\n        {\n          \"FacilityOperatorID\": \"123-XXX\",\n          \"FacilityOperatorOrganisationID\": \"osdu:master-data--Organisation:Operator01:\",\n          \"EffectiveDateTime\": \"2020-02-13T09:13:15.55Z\",\n          \"TerminationDateTime\": \"\"\n        }\n      ],      \n      \"CurrentOperatorID\": \"osdu:master-data--Organisation:Operator01:\",      \n      \"OperatingEnvironmentID\": \"osdu:reference-data--OperatingEnvironment:Offshore:\",      \n      \"FacilityStates\": [\n        {\n          \"EffectiveDateTime\": \"2020-02-13T09:13:15.55Z\",\n          \"TerminationDateTime\": \"2020-02-13T09:13:15.55Z\",\n          \"FacilityStateTypeID\": \"osdu:reference-data--FacilityStateType:Operating:\"\n        }\n      ],\n      \"FacilityEvents\": [\n        {\n          \"FacilityEventTypeID\": \"osdu:reference-data--FacilityEventType:DrillingStart:\",\n          \"EffectiveDateTime\": \"2012-12-03T02:30:00+08:00\"\n        },\n        {\n          \"FacilityEventTypeID\": \"osdu:reference-data--FacilityEventType:DrillingFinish:\",\n          \"EffectiveDateTime\": \"2012-12-25T19:30:00+08:00\"\n        }\n      ],\n      \"FacilitySpecifications\": [],\n      \"WellID\": \"osdu:master-data--Well:Well888:\",\n      \"SequenceNumber\": 2,\n      \"VerticalMeasurements\": [\n        {\n          \"VerticalMeasurementID\": \"\",          \n          \"EffectiveDateTime\": \"2020-02-13T09:13:15.55Z\",\n          \"VerticalMeasurement\": 12345.6,\n          \"TerminationDateTime\": \"\",\n          \"VerticalMeasurementTypeID\": \"osdu:reference-data--VerticalMeasurementType:TotalDepth:\",\n          \"VerticalMeasurementPathID\": \"osdu:reference-data--VerticalMeasurementPath:MD:\",       \n          \"VerticalMeasurementUnitOfMeasureID\": \"osdu:reference-data--UnitOfMeasure:m:\",\n          \"VerticalCRSID\": \"osdu:reference-data--CoordinateReferenceSystem:BoundProjected:EPSG::32021_EPSG::15851:\",\n          \"VerticalReferenceID\": \"XYZ\",\n          \"VerticalMeasurementDescription\": \"XYZ Description\"\n        }\n      ],\n      \"DrillingReasons\": [\n        {\n          \"DrillingReasonTypeID\": \"osdu:reference-data--DrillingReasonType:Development:\",\n          \"EffectiveDateTime\": \"2020-02-13T09:13:15.55Z\",\n          \"TerminationDateTime\": \"2020-02-13T09:13:15.55Z\"\n        }\n      ],    \n      \"TrajectoryTypeID\": \"osdu:reference-data--WellboreTrajectoryType:Vertical:\",      \n      \"TargetFormation\": \"osdu:reference-data--GeologicalFormation:Bakken:\",\n      \"DefaultVerticalMeasurementID\": \"XYZ\",\n      \"ProjectedBottomHoleLocation\": {\n        \"SpatialLocationCoordinatesDate\": \"2020-02-13T09:13:15.55Z\",\n        \"QuantitativeAccuracyBandID\": \"osdu:reference-data--QuantitativeAccuracyBand:Length.LessThan1m:\",\n        \"QualitativeSpatialAccuracyTypeID\": \"osdu:reference-data--QualitativeSpatialAccuracyType:Assumed:\",\n        \"CoordinateQualityCheckPerformedBy\": \"Example CoordinateQualityCheckPerformedBy\",\n        \"CoordinateQualityCheckDateTime\": \"2020-02-13T09:13:15.55Z\",\n        \"CoordinateQualityCheckRemarks\": [\n          \"Example CoordinateQualityCheckRemarks\"\n        ],\n        \"AsIngestedCoordinates\": {\n          \"type\": \"AnyCrsFeatureCollection\",\n          \"CoordinateReferenceSystemID\": \"osdu:reference-data--CoordinateReferenceSystem:BoundProjected:EPSG::32021_EPSG::15851:\",\n          \"VerticalCoordinateReferenceSystemID\": \"osdu:reference-data--CoordinateReferenceSystem:Vertical:EPSG::5714:\",\n          \"VerticalUnitID\": \"osdu:reference-data--UnitOfMeasure:m:\",\n          \"persistableReferenceCrs\": \"{\\\"authCode\\\":{\\\"auth\\\":\\\"OSDU\\\",\\\"code\\\":\\\"32021079\\\"},\\\"lateBoundCRS\\\":{\\\"authCode\\\":{\\\"auth\\\":\\\"EPSG\\\",\\\"code\\\":\\\"32021\\\"},\\\"name\\\":\\\"NAD_1927_StatePlane_North_Dakota_South_FIPS_3302\\\",\\\"type\\\":\\\"LBC\\\",\\\"ver\\\":\\\"PE_10_9_1\\\",\\\"wkt\\\":\\\"PROJCS[\\\\\\\"NAD_1927_StatePlane_North_Dakota_South_FIPS_3302\\\\\\\",GEOGCS[\\\\\\\"GCS_North_American_1927\\\\\\\",DATUM[\\\\\\\"D_North_American_1927\\\\\\\",SPHEROID[\\\\\\\"Clarke_1866\\\\\\\",6378206.4,294.9786982]],PRIMEM[\\\\\\\"Greenwich\\\\\\\",0.0],UNIT[\\\\\\\"Degree\\\\\\\",0.0174532925199433]],PROJECTION[\\\\\\\"Lambert_Conformal_Conic\\\\\\\"],PARAMETER[\\\\\\\"False_Easting\\\\\\\",2000000.0],PARAMETER[\\\\\\\"False_Northing\\\\\\\",0.0],PARAMETER[\\\\\\\"Central_Meridian\\\\\\\",-100.5],PARAMETER[\\\\\\\"Standard_Parallel_1\\\\\\\",46.18333333333333],PARAMETER[\\\\\\\"Standard_Parallel_2\\\\\\\",47.48333333333333],PARAMETER[\\\\\\\"Latitude_Of_Origin\\\\\\\",45.66666666666666],UNIT[\\\\\\\"Foot_US\\\\\\\",0.3048006096012192],AUTHORITY[\\\\\\\"EPSG\\\\\\\",32021]]\\\"},\\\"name\\\":\\\"NAD27 * OGP-Usa Conus / North Dakota CS27 South zone [32021,15851]\\\",\\\"singleCT\\\":{\\\"authCode\\\":{\\\"auth\\\":\\\"EPSG\\\",\\\"code\\\":\\\"15851\\\"},\\\"name\\\":\\\"NAD_1927_To_WGS_1984_79_CONUS\\\",\\\"type\\\":\\\"ST\\\",\\\"ver\\\":\\\"PE_10_9_1\\\",\\\"wkt\\\":\\\"GEOGTRAN[\\\\\\\"NAD_1927_To_WGS_1984_79_CONUS\\\\\\\",GEOGCS[\\\\\\\"GCS_North_American_1927\\\\\\\",DATUM[\\\\\\\"D_North_American_1927\\\\\\\",SPHEROID[\\\\\\\"Clarke_1866\\\\\\\",6378206.4,294.9786982]],PRIMEM[\\\\\\\"Greenwich\\\\\\\",0.0],UNIT[\\\\\\\"Degree\\\\\\\",0.0174532925199433]],GEOGCS[\\\\\\\"GCS_WGS_1984\\\\\\\",DATUM[\\\\\\\"D_WGS_1984\\\\\\\",SPHEROID[\\\\\\\"WGS_1984\\\\\\\",6378137.0,298.257223563]],PRIMEM[\\\\\\\"Greenwich\\\\\\\",0.0],UNIT[\\\\\\\"Degree\\\\\\\",0.0174532925199433]],METHOD[\\\\\\\"NADCON\\\\\\\"],PARAMETER[\\\\\\\"Dataset_conus\\\\\\\",0.0],OPERATIONACCURACY[5.0],AUTHORITY[\\\\\\\"EPSG\\\\\\\",15851]]\\\"},\\\"type\\\":\\\"EBC\\\",\\\"ver\\\":\\\"PE_10_9_1\\\"}\",\n          \"persistableReferenceVerticalCrs\": \"{\\\"authCode\\\":{\\\"auth\\\":\\\"EPSG\\\",\\\"code\\\":\\\"5714\\\"},\\\"name\\\":\\\"MSL_Height\\\",\\\"type\\\":\\\"LBC\\\",\\\"ver\\\":\\\"PE_10_9_1\\\",\\\"wkt\\\":\\\"VERTCS[\\\\\\\"MSL_Height\\\\\\\",VDATUM[\\\\\\\"Mean_Sea_Level\\\\\\\"],PARAMETER[\\\\\\\"Vertical_Shift\\\\\\\",0.0],PARAMETER[\\\\\\\"Direction\\\\\\\",1.0],UNIT[\\\\\\\"Meter\\\\\\\",1.0],AUTHORITY[\\\\\\\"EPSG\\\\\\\",5714]]\\\"}\",\n          \"persistableReferenceUnitZ\": \"{\\\"scaleOffset\\\":{\\\"scale\\\":1.0,\\\"offset\\\":0.0},\\\"symbol\\\":\\\"m\\\",\\\"baseMeasurement\\\":{\\\"ancestry\\\":\\\"Length\\\",\\\"type\\\":\\\"UM\\\"},\\\"type\\\":\\\"USO\\\"}\",\n          \"features\": [\n            {\n              \"type\": \"AnyCrsFeature\",\n              \"properties\": {},\n              \"geometry\": {\n                \"type\": \"AnyCrsPoint\",\n                \"coordinates\": [\n                  12345.6,\n                  12345.6\n                ],\n                \"bbox\": [\n                  12345.6,\n                  12345.6,\n                  12345.6,\n                  12345.6\n                ]\n              },\n              \"bbox\": [\n                12345.6,\n                12345.6,\n                12345.6,\n                12345.6\n              ]\n            }\n          ],\n          \"bbox\": [\n            12345.6,\n            12345.6,\n            12345.6,\n            12345.6\n          ]\n        },\n        \"Wgs84Coordinates\": {\n          \"type\": \"FeatureCollection\",\n          \"features\": [\n            {\n              \"type\": \"Feature\",\n              \"properties\": {},\n              \"geometry\": {\n                \"type\": \"Point\",\n                \"coordinates\": [\n                  12345.6,\n                  12345.6\n                ],\n                \"bbox\": [\n                  12345.6,\n                  12345.6,\n                  12345.6,\n                  12345.6\n                ]\n              },\n              \"bbox\": [\n                12345.6,\n                12345.6,\n                12345.6,\n                12345.6\n              ]\n            }\n          ],\n          \"bbox\": [\n            12345.6,\n            12345.6,\n            12345.6,\n            12345.6\n          ]\n        },        \n        \"SpatialParameterTypeID\": \"osdu:reference-data--SpatialParameterType:Outline:\",\n        \"SpatialGeometryTypeID\": \"osdu:reference-data--SpatialGeometryType:Point:\"\n      },\n      \"GeographicBottomHoleLocation\": {\n        \"SpatialLocationCoordinatesDate\": \"2020-02-13T09:13:15.55Z\",\n        \"QuantitativeAccuracyBandID\": \"osdu:reference-data--QuantitativeAccuracyBand:Length.LessThan1m:\",\n        \"QualitativeSpatialAccuracyTypeID\": \"osdu:reference-data--QualitativeSpatialAccuracyType:Assumed:\",\n        \"CoordinateQualityCheckPerformedBy\": \"Example CoordinateQualityCheckPerformedBy\",\n        \"CoordinateQualityCheckDateTime\": \"2020-02-13T09:13:15.55Z\",\n        \"CoordinateQualityCheckRemarks\": [\n          \"Example CoordinateQualityCheckRemarks\"\n        ],\n        \"AsIngestedCoordinates\": {\n          \"type\": \"AnyCrsFeatureCollection\",\n          \"CoordinateReferenceSystemID\": \"osdu:reference-data--CoordinateReferenceSystem:BoundProjected:EPSG::32021_EPSG::15851:\",\n          \"VerticalCoordinateReferenceSystemID\": \"osdu:reference-data--CoordinateReferenceSystem:Vertical:EPSG::5714:\",\n          \"VerticalUnitID\": \"osdu:reference-data--UnitOfMeasure:m:\",\n          \"persistableReferenceCrs\": \"{\\\"authCode\\\":{\\\"auth\\\":\\\"OSDU\\\",\\\"code\\\":\\\"32021079\\\"},\\\"lateBoundCRS\\\":{\\\"authCode\\\":{\\\"auth\\\":\\\"EPSG\\\",\\\"code\\\":\\\"32021\\\"},\\\"name\\\":\\\"NAD_1927_StatePlane_North_Dakota_South_FIPS_3302\\\",\\\"type\\\":\\\"LBC\\\",\\\"ver\\\":\\\"PE_10_9_1\\\",\\\"wkt\\\":\\\"PROJCS[\\\\\\\"NAD_1927_StatePlane_North_Dakota_South_FIPS_3302\\\\\\\",GEOGCS[\\\\\\\"GCS_North_American_1927\\\\\\\",DATUM[\\\\\\\"D_North_American_1927\\\\\\\",SPHEROID[\\\\\\\"Clarke_1866\\\\\\\",6378206.4,294.9786982]],PRIMEM[\\\\\\\"Greenwich\\\\\\\",0.0],UNIT[\\\\\\\"Degree\\\\\\\",0.0174532925199433]],PROJECTION[\\\\\\\"Lambert_Conformal_Conic\\\\\\\"],PARAMETER[\\\\\\\"False_Easting\\\\\\\",2000000.0],PARAMETER[\\\\\\\"False_Northing\\\\\\\",0.0],PARAMETER[\\\\\\\"Central_Meridian\\\\\\\",-100.5],PARAMETER[\\\\\\\"Standard_Parallel_1\\\\\\\",46.18333333333333],PARAMETER[\\\\\\\"Standard_Parallel_2\\\\\\\",47.48333333333333],PARAMETER[\\\\\\\"Latitude_Of_Origin\\\\\\\",45.66666666666666],UNIT[\\\\\\\"Foot_US\\\\\\\",0.3048006096012192],AUTHORITY[\\\\\\\"EPSG\\\\\\\",32021]]\\\"},\\\"name\\\":\\\"NAD27 * OGP-Usa Conus / North Dakota CS27 South zone [32021,15851]\\\",\\\"singleCT\\\":{\\\"authCode\\\":{\\\"auth\\\":\\\"EPSG\\\",\\\"code\\\":\\\"15851\\\"},\\\"name\\\":\\\"NAD_1927_To_WGS_1984_79_CONUS\\\",\\\"type\\\":\\\"ST\\\",\\\"ver\\\":\\\"PE_10_9_1\\\",\\\"wkt\\\":\\\"GEOGTRAN[\\\\\\\"NAD_1927_To_WGS_1984_79_CONUS\\\\\\\",GEOGCS[\\\\\\\"GCS_North_American_1927\\\\\\\",DATUM[\\\\\\\"D_North_American_1927\\\\\\\",SPHEROID[\\\\\\\"Clarke_1866\\\\\\\",6378206.4,294.9786982]],PRIMEM[\\\\\\\"Greenwich\\\\\\\",0.0],UNIT[\\\\\\\"Degree\\\\\\\",0.0174532925199433]],GEOGCS[\\\\\\\"GCS_WGS_1984\\\\\\\",DATUM[\\\\\\\"D_WGS_1984\\\\\\\",SPHEROID[\\\\\\\"WGS_1984\\\\\\\",6378137.0,298.257223563]],PRIMEM[\\\\\\\"Greenwich\\\\\\\",0.0],UNIT[\\\\\\\"Degree\\\\\\\",0.0174532925199433]],METHOD[\\\\\\\"NADCON\\\\\\\"],PARAMETER[\\\\\\\"Dataset_conus\\\\\\\",0.0],OPERATIONACCURACY[5.0],AUTHORITY[\\\\\\\"EPSG\\\\\\\",15851]]\\\"},\\\"type\\\":\\\"EBC\\\",\\\"ver\\\":\\\"PE_10_9_1\\\"}\",\n          \"persistableReferenceVerticalCrs\": \"{\\\"authCode\\\":{\\\"auth\\\":\\\"EPSG\\\",\\\"code\\\":\\\"5714\\\"},\\\"name\\\":\\\"MSL_Height\\\",\\\"type\\\":\\\"LBC\\\",\\\"ver\\\":\\\"PE_10_9_1\\\",\\\"wkt\\\":\\\"VERTCS[\\\\\\\"MSL_Height\\\\\\\",VDATUM[\\\\\\\"Mean_Sea_Level\\\\\\\"],PARAMETER[\\\\\\\"Vertical_Shift\\\\\\\",0.0],PARAMETER[\\\\\\\"Direction\\\\\\\",1.0],UNIT[\\\\\\\"Meter\\\\\\\",1.0],AUTHORITY[\\\\\\\"EPSG\\\\\\\",5714]]\\\"}\",\n          \"persistableReferenceUnitZ\": \"{\\\"scaleOffset\\\":{\\\"scale\\\":1.0,\\\"offset\\\":0.0},\\\"symbol\\\":\\\"m\\\",\\\"baseMeasurement\\\":{\\\"ancestry\\\":\\\"Length\\\",\\\"type\\\":\\\"UM\\\"},\\\"type\\\":\\\"USO\\\"}\",\n          \"features\": [\n            {\n              \"type\": \"AnyCrsFeature\",\n              \"properties\": {},\n              \"geometry\": {\n                \"type\": \"AnyCrsPoint\",\n                \"coordinates\": [\n                  12345.6,\n                  12345.6\n                ],\n                \"bbox\": [\n                  12345.6,\n                  12345.6,\n                  12345.6,\n                  12345.6\n                ]\n              },\n              \"bbox\": [\n                12345.6,\n                12345.6,\n                12345.6,\n                12345.6\n              ]\n            }\n          ],\n          \"bbox\": [\n            12345.6,\n            12345.6,\n            12345.6,\n            12345.6\n          ]\n        },\n        \"Wgs84Coordinates\": {\n          \"type\": \"FeatureCollection\",\n          \"features\": [\n            {\n              \"type\": \"Feature\",\n              \"properties\": {},\n              \"geometry\": {\n                \"type\": \"Point\",\n                \"coordinates\": [\n                  12345.6,\n                  12345.6\n                ],\n                \"bbox\": [\n                  12345.6,\n                  12345.6,\n                  12345.6,\n                  12345.6\n                ]\n              },\n              \"bbox\": [\n                12345.6,\n                12345.6,\n                12345.6,\n                12345.6\n              ]\n            }\n          ],\n          \"bbox\": [\n            12345.6,\n            12345.6,\n            12345.6,\n            12345.6\n          ]\n        },        \n        \"SpatialParameterTypeID\": \"osdu:reference-data--SpatialParameterType:Outline:\",\n        \"SpatialGeometryTypeID\": \"osdu:reference-data--SpatialGeometryType:Point:\"\n      },\n      \"BusinessIntentionID\": \"osdu:reference-data--WellBusinessIntention:Appraise:\",\n      \"RoleID\": \"osdu:reference-data--WellRole:Produce:\",\n      \"InterestTypeID\": \"osdu:reference-data--WellInterestType:Yes:\",\n      \"HistoricalInterests\": [\n        {\n          \"InterestTypeID\": \"osdu:reference-data--WellInterestType:Yes:\",\n          \"EffectiveDateTime\": \"2020-02-13\",\n          \"TerminationDateTime\": \"2020-02-13\"\n        }\n      ],\n      \"WellboreTrajectoryTypeID\": \"osdu:reference-data--WellboreTrajectoryType:Vertical:\",\n      \"PrimaryProductTypeID\": \"osdu:reference-data--WellProductType:Oil.Light:\",\n      \"SecondaryProductTypeID\": \"osdu:reference-data--WellProductType:Gas:\",    \n      \"ShowProductTypeID\": \"osdu:reference-data--WellProductType:Gas:\",\n      \"ConditionID\": \"osdu:reference-data--WellCondition:Active:\",\n      \"FluidDirectionID\": \"osdu:reference-data--WellFluidDirection:OutFlow:\",\n      \"OutcomeID\": \"osdu:reference-data--WellBusinessIntentionOutcome:Achieved:\",\n      \"StatusSummaryID\": \"osdu:reference-data--WellStatusSummary:Operating:\",\n      \"ExtensionProperties\": {}\n    }\n  }\n]"},"parameters":[{"name":"skipdupes","value":"true","disabled":true}],"headers":[{"name":"data-partition-id","value":"{{ _['data-partition-id'] }}","id":"pair_1b8e4fd8991f4b56ad693c3ffcc400fb"},{"name":"Accept","value":"application/json","id":"pair_12b5af01be3c49bca502c0f5049c1235"},{"name":"Content-Type","value":"application/json","id":"pair_e7cebbfb86d34ed9b85f9d85a0d48d94"}],"authentication":{"type":"oauth2","grantType":"client_credentials","accessTokenUrl":"{{ _.client_credentials }}","clientId":"{{ _.CLIENT_ID }}","clientSecret":"{{ _.CLIENT_SECRET }}"},"metaSortKey":-1686074148895.625,"isPrivate":false,"settingStoreCookies":true,"settingSendCookies":true,"settingDisableRenderRequestBody":false,"settingEncodeUrl":true,"settingRebuildPath":true,"settingFollowRedirects":"global","_type":"request"},{"_id":"req_7eda412741da4dec9ca9c366aaad43e3","parentId":"fld_db739268ae7a46bc99591dc82a25b314","modified":1687444889081,"created":1687285904581,"url":"{{ _.STORAGE_HOST }}/records","name":"Storage API - Create Field record with kind","description":"","method":"PUT","body":{"mimeType":"application/json","text":"[\n\t{\n\t\t\"id\": \"osdu:master-data--Field:FieldName\",\n\t\t\"kind\": \"osdu:wks:master-data--Field:1.0.0\",\t\t\n\t\t\"acl\": {\n\t\t\t\"owners\": [\n\t\t\t\t\"{{ _.New_OwnerDataGroup }}@{{ _.domain }}\"\n\t\t\t],\n\t\t\t\"viewers\": [\n\t\t\t\t\"{{ _.New_ViewerDataGroup }}@{{ _.domain }}\"\n\t\t\t]\n\t\t},\n\t\t\"legal\": {\n\t\t\t\"legaltags\": [\n\t\t\t\t\"{{ _.tagName }}\"\n\t\t\t],\n\t\t\t\"otherRelevantDataCountries\": [\n\t\t\t\t\"BR\"\n\t\t\t],\n\t\t\t\"status\": \"compliant\"\n\t\t},\n\t\t\"meta\": [],\n\t\t\"data\": {\n\t\t\t\"Source\": \"Libra\",\n\t\t\t\"ExistenceKind\": \"osdu:reference-data--ExistenceKind:Active:\",\n\t\t\t\"GeoContexts\": [\n\t\t\t\t{\n\t\t\t\t\t\"GeoPoliticalEntityID\": \"BR\",\n\t\t\t\t\t\"GeoPoliticalEntityTypeID\": \"osdu:reference-data--GeoPoliticalEntityType:Region:\"\n\t\t\t\t}\n\t\t\t],\n\t\t\t\"TechnicalAssuranceTypeID\": \"osdu:reference-data--TechnicalAssuranceType:Certified:\",\n\t\t\t\"FieldName\": \"Mero field\",\n\t\t\t\"FieldDescription\": \"Mero is the third largest pre-salt oil field, behind only Buzios and Tupi, highlights Petrobras. The platform was built and is being operated by the Japanese Modec.\",\n\t\t\t\"EffectiveDate\": \"2020-02-13T09:13:15.55Z\",\n\t\t\t\"TerminationDate\": \"2020-02-13T09:13:15.55Z\",\n\t\t\t\"ExtensionProperties\": {}\n\t\t}\n\t}\n]"},"parameters":[{"name":"skipdupes","value":"true","disabled":true}],"headers":[{"name":"data-partition-id","value":"{{ _['data-partition-id'] }}","id":"pair_1b8e4fd8991f4b56ad693c3ffcc400fb"},{"name":"Accept","value":"application/json","id":"pair_12b5af01be3c49bca502c0f5049c1235"},{"name":"Content-Type","value":"application/json","id":"pair_e7cebbfb86d34ed9b85f9d85a0d48d94"}],"authentication":{"type":"oauth2","grantType":"client_credentials","accessTokenUrl":"{{ _.client_credentials }}","clientId":"{{ _.CLIENT_ID }}","clientSecret":"{{ _.CLIENT_SECRET }}"},"metaSortKey":-1686074148895.5,"isPrivate":false,"settingStoreCookies":true,"settingSendCookies":true,"settingDisableRenderRequestBody":false,"settingEncodeUrl":true,"settingRebuildPath":true,"settingFollowRedirects":"global","_type":"request"},{"_id":"req_6abc8222db184986bac22a514c120ce8","parentId":"fld_db739268ae7a46bc99591dc82a25b314","modified":1687445338070,"created":1687444426741,"url":"{{ _.STORAGE_HOST }}/records","name":"Storage API - Create Basin record with kind","description":"","method":"PUT","body":{"mimeType":"application/json","text":"[\n\t{\n\t\t\"id\": \"osdu:master-data--Basin:BasinName\",\n\t\t\"kind\": \"osdu:wks:master-data--Basin:1.0.0\",\n\t\t\"acl\": {\n\t\t\t\"owners\": [\n\t\t\t\t\"{{ _.New_OwnerDataGroup }}@{{ _.domain }}\"\n\t\t\t],\n\t\t\t\"viewers\": [\n\t\t\t\t\"{{ _.New_ViewerDataGroup }}@{{ _.domain }}\"\n\t\t\t]\n\t\t},\n\t\t\"legal\": {\n\t\t\t\"legaltags\": [\n\t\t\t\t\"{{ _.tagName }}\"\n\t\t\t],\n\t\t\t\"otherRelevantDataCountries\": [\n\t\t\t\t\"BR\"\n\t\t\t],\n\t\t\t\"status\": \"compliant\"\n\t\t},\n\t\t\"meta\": [],\n\t\t\"data\": {\n\t\t\t\"Source\": \"Company name or system\",\n\t\t\t\"GeoContexts\": [\n\t\t\t\t{\n\t\t\t\t\t\"FieldID\": \"osdu:master-data--Field:FielName:\",\n\t\t\t\t\t\"GeoPoliticalEntityID\": \"BR\",\n\t\t\t\t\t\"GeoPoliticalEntityTypeID\": \"osdu:reference-data--GeoPoliticalEntityType:Region:\"\n\t\t\t\t}\n\t\t\t],\n\t\t\t\"SpatialLocation\": {\n\t\t\t\t\"SpatialLocationCoordinatesDate\": \"2020-02-13T09:13:15.55Z\",\n\t\t\t\t\"QuantitativeAccuracyBandID\": \"osdu:reference-data--QuantitativeAccuracyBand:Length.LessThan1m:\",\n\t\t\t\t\"QualitativeSpatialAccuracyTypeID\": \"osdu:reference-data--QualitativeSpatialAccuracyType:Assumed:\",\n\t\t\t\t\"CoordinateQualityCheckPerformedBy\": \"Example CoordinateQualityCheckPerformedBy\",\n\t\t\t\t\"CoordinateQualityCheckDateTime\": \"2020-02-13T09:13:15.55Z\",\n\t\t\t\t\"CoordinateQualityCheckRemarks\": [\n\t\t\t\t\t\"Example CoordinateQualityCheckRemarks\"\n\t\t\t\t],\n\t\t\t\t\"AsIngestedCoordinates\": {\n\t\t\t\t\t\"type\": \"AnyCrsFeatureCollection\",\n\t\t\t\t\t\"CoordinateReferenceSystemID\": \"osdu:reference-data--CoordinateReferenceSystem:BoundProjected:EPSG::32021_EPSG::15851:\",\n\t\t\t\t\t\"VerticalCoordinateReferenceSystemID\": \"osdu:reference-data--CoordinateReferenceSystem:Vertical:EPSG::5714:\",\n\t\t\t\t\t\"persistableReferenceCrs\": \"{\\\"authCode\\\":{\\\"auth\\\":\\\"OSDU\\\",\\\"code\\\":\\\"32021079\\\"},\\\"lateBoundCRS\\\":{\\\"authCode\\\":{\\\"auth\\\":\\\"EPSG\\\",\\\"code\\\":\\\"32021\\\"},\\\"name\\\":\\\"NAD_1927_StatePlane_North_Dakota_South_FIPS_3302\\\",\\\"type\\\":\\\"LBC\\\",\\\"ver\\\":\\\"PE_10_9_1\\\",\\\"wkt\\\":\\\"PROJCS[\\\\\\\"NAD_1927_StatePlane_North_Dakota_South_FIPS_3302\\\\\\\",GEOGCS[\\\\\\\"GCS_North_American_1927\\\\\\\",DATUM[\\\\\\\"D_North_American_1927\\\\\\\",SPHEROID[\\\\\\\"Clarke_1866\\\\\\\",6378206.4,294.9786982]],PRIMEM[\\\\\\\"Greenwich\\\\\\\",0.0],UNIT[\\\\\\\"Degree\\\\\\\",0.0174532925199433]],PROJECTION[\\\\\\\"Lambert_Conformal_Conic\\\\\\\"],PARAMETER[\\\\\\\"False_Easting\\\\\\\",2000000.0],PARAMETER[\\\\\\\"False_Northing\\\\\\\",0.0],PARAMETER[\\\\\\\"Central_Meridian\\\\\\\",-100.5],PARAMETER[\\\\\\\"Standard_Parallel_1\\\\\\\",46.18333333333333],PARAMETER[\\\\\\\"Standard_Parallel_2\\\\\\\",47.48333333333333],PARAMETER[\\\\\\\"Latitude_Of_Origin\\\\\\\",45.66666666666666],UNIT[\\\\\\\"Foot_US\\\\\\\",0.3048006096012192],AUTHORITY[\\\\\\\"EPSG\\\\\\\",32021]]\\\"},\\\"name\\\":\\\"NAD27 * OGP-Usa Conus / North Dakota CS27 South zone [32021,15851]\\\",\\\"singleCT\\\":{\\\"authCode\\\":{\\\"auth\\\":\\\"EPSG\\\",\\\"code\\\":\\\"15851\\\"},\\\"name\\\":\\\"NAD_1927_To_WGS_1984_79_CONUS\\\",\\\"type\\\":\\\"ST\\\",\\\"ver\\\":\\\"PE_10_9_1\\\",\\\"wkt\\\":\\\"GEOGTRAN[\\\\\\\"NAD_1927_To_WGS_1984_79_CONUS\\\\\\\",GEOGCS[\\\\\\\"GCS_North_American_1927\\\\\\\",DATUM[\\\\\\\"D_North_American_1927\\\\\\\",SPHEROID[\\\\\\\"Clarke_1866\\\\\\\",6378206.4,294.9786982]],PRIMEM[\\\\\\\"Greenwich\\\\\\\",0.0],UNIT[\\\\\\\"Degree\\\\\\\",0.0174532925199433]],GEOGCS[\\\\\\\"GCS_WGS_1984\\\\\\\",DATUM[\\\\\\\"D_WGS_1984\\\\\\\",SPHEROID[\\\\\\\"WGS_1984\\\\\\\",6378137.0,298.257223563]],PRIMEM[\\\\\\\"Greenwich\\\\\\\",0.0],UNIT[\\\\\\\"Degree\\\\\\\",0.0174532925199433]],METHOD[\\\\\\\"NADCON\\\\\\\"],PARAMETER[\\\\\\\"Dataset_conus\\\\\\\",0.0],OPERATIONACCURACY[5.0],AUTHORITY[\\\\\\\"EPSG\\\\\\\",15851]]\\\"},\\\"type\\\":\\\"EBC\\\",\\\"ver\\\":\\\"PE_10_9_1\\\"}\",\n\t\t\t\t\t\"persistableReferenceVerticalCrs\": \"{\\\"authCode\\\":{\\\"auth\\\":\\\"EPSG\\\",\\\"code\\\":\\\"5714\\\"},\\\"name\\\":\\\"MSL_Height\\\",\\\"type\\\":\\\"LBC\\\",\\\"ver\\\":\\\"PE_10_9_1\\\",\\\"wkt\\\":\\\"VERTCS[\\\\\\\"MSL_Height\\\\\\\",VDATUM[\\\\\\\"Mean_Sea_Level\\\\\\\"],PARAMETER[\\\\\\\"Vertical_Shift\\\\\\\",0.0],PARAMETER[\\\\\\\"Direction\\\\\\\",1.0],UNIT[\\\\\\\"Meter\\\\\\\",1.0],AUTHORITY[\\\\\\\"EPSG\\\\\\\",5714]]\\\"}\",\n\t\t\t\t\t\"persistableReferenceUnitZ\": \"{\\\"scaleOffset\\\":{\\\"scale\\\":1.0,\\\"offset\\\":0.0},\\\"symbol\\\":\\\"m\\\",\\\"baseMeasurement\\\":{\\\"ancestry\\\":\\\"Length\\\",\\\"type\\\":\\\"UM\\\"},\\\"type\\\":\\\"USO\\\"}\",\n\t\t\t\t\t\"features\": [\n\t\t\t\t\t\t{\n\t\t\t\t\t\t\t\"type\": \"AnyCrsFeature\",\n\t\t\t\t\t\t\t\"properties\": {},\n\t\t\t\t\t\t\t\"geometry\": {\n\t\t\t\t\t\t\t\t\"type\": \"AnyCrsPoint\",\n\t\t\t\t\t\t\t\t\"coordinates\": [\n\t\t\t\t\t\t\t\t\t12345.6,\n\t\t\t\t\t\t\t\t\t12345.6\n\t\t\t\t\t\t\t\t],\n\t\t\t\t\t\t\t\t\"bbox\": [\n\t\t\t\t\t\t\t\t\t12345.6,\n\t\t\t\t\t\t\t\t\t12345.6,\n\t\t\t\t\t\t\t\t\t12345.6,\n\t\t\t\t\t\t\t\t\t12345.6\n\t\t\t\t\t\t\t\t]\n\t\t\t\t\t\t\t},\n\t\t\t\t\t\t\t\"bbox\": [\n\t\t\t\t\t\t\t\t12345.6,\n\t\t\t\t\t\t\t\t12345.6,\n\t\t\t\t\t\t\t\t12345.6,\n\t\t\t\t\t\t\t\t12345.6\n\t\t\t\t\t\t\t]\n\t\t\t\t\t\t}\n\t\t\t\t\t],\n\t\t\t\t\t\"bbox\": [\n\t\t\t\t\t\t12345.6,\n\t\t\t\t\t\t12345.6,\n\t\t\t\t\t\t12345.6,\n\t\t\t\t\t\t12345.6\n\t\t\t\t\t]\n\t\t\t\t},\n\t\t\t\t\"Wgs84Coordinates\": {\n\t\t\t\t\t\"type\": \"FeatureCollection\",\n\t\t\t\t\t\"features\": [\n\t\t\t\t\t\t{\n\t\t\t\t\t\t\t\"type\": \"Feature\",\n\t\t\t\t\t\t\t\"properties\": {},\n\t\t\t\t\t\t\t\"geometry\": {\n\t\t\t\t\t\t\t\t\"type\": \"Point\",\n\t\t\t\t\t\t\t\t\"coordinates\": [\n\t\t\t\t\t\t\t\t\t12345.6,\n\t\t\t\t\t\t\t\t\t12345.6\n\t\t\t\t\t\t\t\t],\n\t\t\t\t\t\t\t\t\"bbox\": [\n\t\t\t\t\t\t\t\t\t12345.6,\n\t\t\t\t\t\t\t\t\t12345.6,\n\t\t\t\t\t\t\t\t\t12345.6,\n\t\t\t\t\t\t\t\t\t12345.6\n\t\t\t\t\t\t\t\t]\n\t\t\t\t\t\t\t},\n\t\t\t\t\t\t\t\"bbox\": [\n\t\t\t\t\t\t\t\t12345.6,\n\t\t\t\t\t\t\t\t12345.6,\n\t\t\t\t\t\t\t\t12345.6,\n\t\t\t\t\t\t\t\t12345.6\n\t\t\t\t\t\t\t]\n\t\t\t\t\t\t}\n\t\t\t\t\t],\n\t\t\t\t\t\"bbox\": [\n\t\t\t\t\t\t12345.6,\n\t\t\t\t\t\t12345.6,\n\t\t\t\t\t\t12345.6,\n\t\t\t\t\t\t12345.6\n\t\t\t\t\t]\n\t\t\t\t},\n\t\t\t\t\"SpatialParameterTypeID\": \"osdu:reference-data--SpatialParameterType:Outline:\",\n\t\t\t\t\"SpatialGeometryTypeID\": \"osdu:reference-data--SpatialGeometryType:Point:\"\n\t\t\t},\n\t\t\t\"TechnicalAssuranceTypeID\": \"osdu:reference-data--TechnicalAssuranceType:Certified:\",\n\t\t\t\"BasinName\": \"BasinName\",\n\t\t\t\"BasinDescription\": \"Put here a desciption of the basin.\",\n\t\t\t\"BasinTypeID\": \"osdu:reference-data--BasinType:ArcWrenchOceanContinent:\",\n\t\t\t\"ExtensionProperties\": {}\n\t\t}\n\t}\n]"},"parameters":[{"name":"skipdupes","value":"true","disabled":true}],"headers":[{"name":"data-partition-id","value":"{{ _['data-partition-id'] }}","id":"pair_1b8e4fd8991f4b56ad693c3ffcc400fb"},{"name":"Accept","value":"application/json","id":"pair_12b5af01be3c49bca502c0f5049c1235"},{"name":"Content-Type","value":"application/json","id":"pair_e7cebbfb86d34ed9b85f9d85a0d48d94"}],"authentication":{"type":"oauth2","grantType":"client_credentials","accessTokenUrl":"{{ _.client_credentials }}","clientId":"{{ _.CLIENT_ID }}","clientSecret":"{{ _.CLIENT_SECRET }}"},"metaSortKey":-1686074148895.375,"isPrivate":false,"settingStoreCookies":true,"settingSendCookies":true,"settingDisableRenderRequestBody":false,"settingEncodeUrl":true,"settingRebuildPath":true,"settingFollowRedirects":"global","_type":"request"},{"_id":"req_495176f4d2384fe8999e5c4c6b8f5041","parentId":"fld_db739268ae7a46bc99591dc82a25b314","modified":1687204579601,"created":1686922682354,"url":"{{ _.SCHEMA_HOST }}/schema/{{ _.id }}","name":"Schema API - Get schema by id","description":"","method":"GET","body":{},"parameters":[],"headers":[{"name":"Content-Type","value":"application/json","id":"pair_f6c761221d1a4a328d6b861c2091605e"},{"name":"data-partition-id","value":"{{ _['data-partition-id'] }}","id":"pair_0c9f65fd9335418db820adf69a99acd8"}],"authentication":{"type":"oauth2","grantType":"client_credentials","accessTokenUrl":"{{ _.client_credentials }}","clientId":"{{ _.CLIENT_ID }}","clientSecret":"{{ _.CLIENT_SECRET }}"},"metaSortKey":-1686074148895,"isPrivate":false,"settingStoreCookies":true,"settingSendCookies":true,"settingDisableRenderRequestBody":false,"settingEncodeUrl":true,"settingRebuildPath":true,"settingFollowRedirects":"global","_type":"request"},{"_id":"req_989b2407427049c5a50542ef2e4f1823","parentId":"fld_db739268ae7a46bc99591dc82a25b314","modified":1687204761087,"created":1686922682351,"url":"{{ _.SCHEMA_HOST }}/schema","name":"Schema API - Adds a schema","description":"","method":"POST","body":{"mimeType":"application/json","text":"{\n  \"schemaInfo\": {\n    \"schemaIdentity\": {\n      \"authority\": \"{{ _['schema-authority'] }}\",\n      \"source\": \"wks\",\n      \"entityType\": \"master-data--SchemaTest\",\n      \"schemaVersionMajor\": 1,\n      \"schemaVersionMinor\": 0,\n      \"schemaVersionPatch\": 0,\n      \"id\": \"{{ _['schema-authority'] }}:wks:master-data--SchemaTest:1.0.0\"\n    },\n\t\t\"createdBy\": \"Petwin Data Definition Group\",\n    \"scope\": \"SHARED\",\n    \"status\": \"DEVELOPMENT\"\n  },\n  \"schema\": {    \n    \"$schema\": \"http://json-schema.org/draft-07/schema#\",\n    \"x-osdu-schema-source\": \"osdu:wks:master-data--Reservoir:0.0.0\",\n    \"title\": \"Reservoir\",\n    \"description\": \"O3PO: A rock that contains one or more individual and separate natural accumulations of petroleum that is confined (the oil, not the reservoir) by impermeable rock.\",\n    \"type\": \"object\",\n    \"properties\": {\n      \"id\": {\n        \"description\": \"Previously called ResourceID or SRN which identifies this OSDU resource object without version.\",\n        \"title\": \"Entity ID\",\n        \"type\": \"string\",\n        \"pattern\": \"^[\\\\w\\\\-\\\\.]+:master-data\\\\-\\\\-Reservoir:[\\\\w\\\\-\\\\.\\\\:\\\\%]+$\",\n        \"example\": \"namespace:master-data--Reservoir:19200196-dee7-54c2-b3d0-9c726dd7246c\"\n      },\n      \"kind\": {\n        \"description\": \"The schema identification for the OSDU resource object following the pattern {Namespace}:{Source}:{Type}:{VersionMajor}.{VersionMinor}.{VersionPatch}. The versioning scheme follows the semantic versioning, https://semver.org/.\",\n        \"title\": \"Entity Kind\",\n        \"type\": \"string\",\n        \"pattern\": \"^[\\\\w\\\\-\\\\.]+:[\\\\w\\\\-\\\\.]+:[\\\\w\\\\-\\\\.]+:[0-9]+.[0-9]+.[0-9]+$\",\n        \"example\": \"osdu:wks:master-data--Reservoir:0.0.0\"\n      },\n      \"version\": {\n        \"description\": \"The version number of this OSDU resource; set by the framework.\",\n        \"title\": \"Version Number\",\n        \"type\": \"integer\",\n        \"format\": \"int64\",\n        \"example\": 1562066009929332\n      },\n      \"acl\": {\n        \"description\": \"The access control tags associated with this entity.\",\n        \"title\": \"Access Control List\",\n        \"$ref\": \"{{ _['schema-authority'] }}:wks:AbstractAccessControlList:1.0.0\"\n      },\n      \"legal\": {\n        \"description\": \"The entity's legal tags and compliance status. The actual contents associated with the legal tags is managed by the Compliance Service.\",\n        \"title\": \"Legal Tags\",\n        \"$ref\": \"{{ _['schema-authority'] }}:wks:AbstractLegalTags:1.0.0\"\n      },\n      \"tags\": {\n        \"title\": \"Tag Dictionary\",\n        \"description\": \"A generic dictionary of string keys mapping to string value. Only strings are permitted as keys and values.\",\n        \"type\": \"object\",\n        \"additionalProperties\": {\n          \"type\": \"string\"\n        },\n        \"example\": {\n          \"NameOfKey\": \"String value\"\n        }\n      },\n      \"createTime\": {\n        \"description\": \"Timestamp of the time at which initial version of this OSDU resource object was created. Set by the System. The value is a combined date-time string in ISO-8601 given in UTC.\",\n        \"title\": \"Resource Object Creation DateTime\",\n        \"type\": \"string\",\n        \"format\": \"date-time\",\n        \"example\": \"2020-12-16T11:46:20.163Z\"\n      },\n      \"createUser\": {\n        \"title\": \"Resource Object Creation User Reference\",\n        \"description\": \"The user reference, which created the first version of this resource object. Set by the System.\",\n        \"type\": \"string\",\n        \"example\": \"some-user@some-company-cloud.com\"\n      },\n      \"modifyTime\": {\n        \"description\": \"Timestamp of the time at which this version of the OSDU resource object was created. Set by the System. The value is a combined date-time string in ISO-8601 given in UTC.\",\n        \"title\": \"Resource Object Version Creation DateTime\",\n        \"type\": \"string\",\n        \"format\": \"date-time\",\n        \"example\": \"2020-12-16T11:52:24.477Z\"\n      },\n      \"modifyUser\": {\n        \"title\": \"Resource Object Version Creation User Reference\",\n        \"description\": \"The user reference, which created this version of this resource object. Set by the System.\",\n        \"type\": \"string\",\n        \"example\": \"some-user@some-company-cloud.com\"\n      },\n      \"ancestry\": {\n        \"description\": \"The links to data, which constitute the inputs, from which this record instance is derived.\",\n        \"title\": \"Ancestry\",\n        \"$ref\": \"{{ _['schema-authority'] }}:wks:AbstractLegalParentList:1.0.0\"\n      },\n      \"meta\": {\n        \"description\": \"The Frame of Reference meta data section linking the named properties to self-contained definitions.\",\n        \"title\": \"Frame of Reference Meta Data\",\n        \"type\": \"array\",\n        \"items\": {\n          \"$ref\": \"{{ _['schema-authority'] }}:wks:AbstractMetaItem:1.0.0\"\n        }\n      },\n      \"data\": {\n        \"allOf\": [\n          {\n            \"$ref\": \"{{ _['schema-authority'] }}:wks:AbstractCommonResources:1.0.0\"\n          },\n          {\n            \"$ref\": \"{{ _['schema-authority'] }}:wks:AbstractMaster:1.1.0\"\n          },\n          {\n            \"type\": \"object\",\n            \"properties\": {\n              \"Name\": {\n                \"type\": \"string\",\n                \"title\": \"Name\",\n                \"description\": \"The name of the Reservoir.\"\n              }\n            },\n            \"title\": \"IndividualProperties\"\n          },\n          {\n            \"type\": \"object\",\n            \"properties\": {\n              \"ExtensionProperties\": {\n                \"type\": \"object\"\n              }\n            },\n            \"title\": \"ExtensionProperties\"\n          }\n        ]\n      }\n    },\n    \"required\": [\n      \"kind\",\n      \"acl\",\n      \"legal\",\n      \"Name\"\n    ],\n    \"additionalProperties\": true,    \n    \"x-osdu-virtual-properties\": {\n      \"data.VirtualProperties.DefaultName\": {\n        \"type\": \"string\",\n        \"priority\": [\n          {\n            \"path\": \"data.Name\"\n          }\n        ]\n      },\n      \"data.VirtualProperties.DefaultLocation\": {\n        \"type\": \"object\",\n        \"priority\": [\n          {\n            \"path\": \"data.SpatialLocation\"\n          }\n        ]\n      }\n    },\n    \"x-osdu-inheriting-from-kind\": []\n  }\n}\n"},"parameters":[],"headers":[{"name":"Content-Type","value":"application/json","id":"pair_36a764d36d0d447d941a38659b1d02bd"},{"name":"data-partition-id","value":"osdu","id":"pair_e628f72cdfe04721b34536af6ee95616"},{"id":"pair_ef06e2a5a0ff41e1a7a66461b75f9da2","name":"Accept","value":"application/json","description":""}],"authentication":{"type":"oauth2","grantType":"client_credentials","clientId":"{{ _.CLIENT_ID }}","clientSecret":"{{ _.CLIENT_SECRET }}","accessTokenUrl":"{{ _.client_credentials }}"},"metaSortKey":-1686074148894,"isPrivate":false,"settingStoreCookies":true,"settingSendCookies":true,"settingDisableRenderRequestBody":false,"settingEncodeUrl":true,"settingRebuildPath":true,"settingFollowRedirects":"global","_type":"request"},{"_id":"req_ece3562cbfb84d989d655d3b366b40d9","parentId":"fld_db739268ae7a46bc99591dc82a25b314","modified":1687546348326,"created":1686922682349,"url":"{{LEGAL_HOST}}/legaltags","name":"Legal API - Create Legal Tag","description":"","method":"POST","body":{"mimeType":"application/json","text":"{\n\t\"name\": \"{{tagName}}\",\n\t\"description\": \"Legal Tag added for VOLVE dataset\",\n\t\"properties\": {\n\t\t\"contractId\": \"No Contract Related\",\n\t\t\"countryOfOrigin\": [\n\t\t\t\"NO\"\n\t\t],\n\t\t\"dataType\": \"Public Domain Data\",\n\t\t\"exportClassification\": \"No License Required\",\n\t\t\"originator\": \"Volve\",\n\t\t\"personalData\": \"No Personal Data\",\n\t\t\"securityClassification\": \"Public\",\n\t\t\"expirationDate\": \"2025-12-25\",\n\t\t\"extensionProperties\": {\n\t\t}\n\t}\n}"},"parameters":[],"headers":[{"name":"Content-Type","value":"application/json","id":"pair_0e7e7684923548d197bd6d644bc9cc99"},{"name":"data-partition-id","value":"{{ _['data-partition-id'] }}","id":"pair_62295ec362bc489a8cc916bbbc897e7b"}],"authentication":{"type":"oauth2","grantType":"client_credentials","accessTokenUrl":"{{ _.client_credentials }}","clientId":"{{ _.CLIENT_ID }}","clientSecret":"{{ _.CLIENT_SECRET }}"},"metaSortKey":-1686074148892,"isPrivate":false,"settingStoreCookies":true,"settingSendCookies":true,"settingDisableRenderRequestBody":false,"settingEncodeUrl":true,"settingRebuildPath":true,"settingFollowRedirects":"global","_type":"request"},{"_id":"req_dfefc9f3f3174541a80bad6f004551cf","parentId":"fld_db739268ae7a46bc99591dc82a25b314","modified":1687547771641,"created":1687547521599,"url":"{{LEGAL_HOST}}/legaltags?valid=true","name":"Legal API - Get valid Legal Tags","description":"","method":"GET","body":{"mimeType":"application/json","text":""},"parameters":[],"headers":[{"name":"Content-Type","value":"application/json","id":"pair_0e7e7684923548d197bd6d644bc9cc99"},{"name":"data-partition-id","value":"{{ _['data-partition-id'] }}","id":"pair_62295ec362bc489a8cc916bbbc897e7b"}],"authentication":{"type":"oauth2","grantType":"client_credentials","accessTokenUrl":"{{ _.client_credentials }}","clientId":"{{ _.CLIENT_ID }}","clientSecret":"{{ _.CLIENT_SECRET }}"},"metaSortKey":-1686074148891,"isPrivate":false,"settingStoreCookies":true,"settingSendCookies":true,"settingDisableRenderRequestBody":false,"settingEncodeUrl":true,"settingRebuildPath":true,"settingFollowRedirects":"global","_type":"request"},{"_id":"req_c15ec48354ca44e78d9281c562394154","parentId":"fld_db739268ae7a46bc99591dc82a25b314","modified":1687552488927,"created":1686922682346,"url":"{{ENTITLEMENTS_HOST}}/groups/{{New_ViewerDataGroup}}@{{ _['data-partition-id'] }}.group/members","name":"Entitlements API - Add members","description":"","method":"POST","body":{"mimeType":"application/json","text":"{\n  \"email\" : \"username@email.com\",\n  \"role\" : \"MEMBER\"\n}\n"},"parameters":[],"headers":[{"name":"Content-Type","value":"application/json","id":"pair_fc2060af4c244cbeb152f6a4aefeaca2"},{"name":"data-partition-id","value":"{{ _['data-partition-id'] }}","id":"pair_4cbd9508069a4ee88a8a7135b35dd42e"}],"authentication":{"type":"oauth2","grantType":"client_credentials","accessTokenUrl":"{{ _.client_credentials }}","clientId":"{{ _.CLIENT_ID }}","clientSecret":"{{ _.CLIENT_SECRET }}"},"metaSortKey":-1686074148890,"isPrivate":false,"settingStoreCookies":true,"settingSendCookies":true,"settingDisableRenderRequestBody":false,"settingEncodeUrl":true,"settingRebuildPath":true,"settingFollowRedirects":"global","_type":"request"},{"_id":"req_05524b716dbf48f6ba62acdafad30204","parentId":"fld_db739268ae7a46bc99591dc82a25b314","modified":1687549908723,"created":1686922682344,"url":"{{ENTITLEMENTS_HOST}}/groups","name":"Entitlements API - Create new data group","description":"","method":"POST","body":{"mimeType":"application/json","text":"{\n  \"name\" :\"data.test.viewers\",\n  \"description\" : \"Certification Test Data group with Viewer access\"\n}"},"parameters":[],"headers":[{"name":"Content-Type","value":"application/json","id":"pair_c8e35e810ae34199aca59d2d204cd22e"},{"name":"data-partition-id","value":"{{ _['data-partition-id'] }}","id":"pair_b61b8a8892a1497bbf390cc30b19ef20"}],"authentication":{"type":"oauth2","grantType":"client_credentials","accessTokenUrl":"{{ _.client_credentials }}","clientId":"{{ _.CLIENT_ID }}","clientSecret":"{{ _.CLIENT_SECRET }}"},"metaSortKey":-1686074148888,"isPrivate":false,"settingStoreCookies":true,"settingSendCookies":true,"settingDisableRenderRequestBody":false,"settingEncodeUrl":true,"settingRebuildPath":true,"settingFollowRedirects":"global","_type":"request"},{"_id":"req_373fe23d7e454491bd51229cfbe4a6db","parentId":"fld_db739268ae7a46bc99591dc82a25b314","modified":1687549492518,"created":1687549427119,"url":"{{ENTITLEMENTS_HOST}}/groups","name":"Entitlements API - Get groups","description":"","method":"GET","body":{"mimeType":"application/json","text":""},"parameters":[],"headers":[{"name":"Content-Type","value":"application/json","id":"pair_be66c63009424e72b19cae3719692f03"},{"name":"data-partition-id","value":"{{ _['data-partition-id'] }}","id":"pair_8794610919de4c86bd464cda3f0a475b"}],"authentication":{"type":"oauth2","grantType":"client_credentials","accessTokenUrl":"{{ _.client_credentials }}","clientId":"{{ _.CLIENT_ID }}","clientSecret":"{{ _.CLIENT_SECRET }}"},"metaSortKey":-1686074148886.5,"isPrivate":false,"settingStoreCookies":true,"settingSendCookies":true,"settingDisableRenderRequestBody":false,"settingEncodeUrl":true,"settingRebuildPath":true,"settingFollowRedirects":"global","_type":"request"},{"_id":"env_0ef90b6f3e2a4afaab7552daaf5376f2","parentId":"wrk_c6691554431948b888837f433dd73cbc","modified":1687798800977,"created":1686922682328,"name":"Base Environment","data":{"data-partition-id":"","tagName":"","domain":"","CLIENT_ID":"","CLIENT_SECRET":"","client_credentials":"","ENTITLEMENTS_HOST":"","New_ViewerDataGroup":"","LEGAL_HOST":"","id":"","New_OwnerDataGroup":"","FILE_HOST":"","WORKFLOW_HOST":"","FileID":"","SCHEMA_HOST":"","schema-authority":"","STORAGE_HOST":"","upload_signedURL":"","file_source":"","SEARCH_HOST":"","record_id":"","download_signed_url":""},"dataPropertyOrder":{"&":["data-partition-id","tagName","domain","CLIENT_ID","CLIENT_SECRET","client_credentials","ENTITLEMENTS_HOST","New_ViewerDataGroup","LEGAL_HOST","id","New_OwnerDataGroup","FILE_HOST","WORKFLOW_HOST","FileID","SCHEMA_HOST","schema-authority","STORAGE_HOST","upload_signedURL","file_source","SEARCH_HOST","record_id","download_signed_url"]},"color":null,"isPrivate":false,"metaSortKey":1686074148933,"_type":"environment"},{"_id":"jar_10e86b792f4b4864875bfa3d0b3a623b","parentId":"wrk_c6691554431948b888837f433dd73cbc","modified":1687784731822,"created":1686922682334,"name":"Default Jar","cookies":[{"key":"KC_RESTART","expires":"1970-01-01T00:00:10.000Z","maxAge":0,"domain":"keycloak.petwin.org","path":"/realms/osdu/","httpOnly":true,"extensions":["Version=1"],"hostOnly":true,"creation":"2023-06-06T18:14:45.643Z","lastAccessed":"2023-06-26T13:05:31.821Z","id":"3599057032448152"}],"_type":"cookie_jar"},{"_id":"spc_167a03f5f6274cc885e720d33adbf87f","parentId":"wrk_c6691554431948b888837f433dd73cbc","modified":1687798614742,"created":1687798614742,"fileName":"TestandoImportacao","contents":"","contentType":"yaml","_type":"api_spec"}]}